[
    {
        "filmId": "53890",
        "name": "Выбери меня",
        "rating": 16,
        "genres": [
            "комедия",
            "мелодрама"
        ],
        "length": 85
    },
    {
        "filmId": "53572",
        "name": "Бордерлендс",
        "rating": 16,
        "genres": [
            "фантастика",
            "боевик",
            "приключения",
            "комедия"
        ],
        "length": 110
    },
    {
        "filmId": "54036",
        "name": "Виселица. Жертва призрака",
        "rating": 18,
        "genres": [
            "ужасы"
        ],
        "length": 80
    },
    {
        "filmId": "54035",
        "name": "Ози: Голос джунглей",
        "rating": 6,
        "genres": [
            "мультфильм",
            "приключения"
        ],
        "length": 87
    },
    {
        "filmId": "53813",
        "name": "Мой дикий друг",
        "rating": 6,
        "genres": [
            "семейный",
            "приключения"
        ],
        "length": 100
    }
]