[
    {
        "date": "14.09",
        "time": "10:45",
        "filmId": "54538",
        "theatre": "Импульс",
        "cost": 300,
        "is3d": false,
        "buyLink": null
    },
    {
        "date": "14.09",
        "time": "12:30",
        "filmId": "54189",
        "theatre": "Импульс",
        "cost": 300,
        "is3d": false,
        "buyLink": null
    },
    {
        "date": "14.09",
        "time": "16:00",
        "filmId": "54305",
        "theatre": "Импульс",
        "cost": 350,
        "is3d": false,
        "buyLink": null
    },
    {
        "date": "14.09",
        "time": "18:00",
        "filmId": "54572",
        "theatre": "Импульс",
        "cost": 350,
        "is3d": false,
        "buyLink": null
    },
    {
        "date": "14.09",
        "time": "19:40",
        "filmId": "54573",
        "theatre": "Импульс",
        "cost": 350,
        "is3d": false,
        "buyLink": null
    },
    {
        "date": "14.09",
        "time": "21:40",
        "filmId": "54590",
        "theatre": "Импульс",
        "cost": 350,
        "is3d": false,
        "buyLink": null
    },
    {
        "date": "15.09",
        "time": "10:45",
        "filmId": "54538",
        "theatre": "Импульс",
        "cost": 300,
        "is3d": false,
        "buyLink": null
    },
    {
        "date": "15.09",
        "time": "12:30",
        "filmId": "54189",
        "theatre": "Импульс",
        "cost": 300,
        "is3d": false,
        "buyLink": null
    },
    {
        "date": "15.09",
        "time": "16:00",
        "filmId": "54305",
        "theatre": "Импульс",
        "cost": 350,
        "is3d": false,
        "buyLink": null
    },
    {
        "date": "15.09",
        "time": "18:00",
        "filmId": "54572",
        "theatre": "Импульс",
        "cost": 350,
        "is3d": false,
        "buyLink": null
    },
    {
        "date": "15.09",
        "time": "19:40",
        "filmId": "54573",
        "theatre": "Импульс",
        "cost": 350,
        "is3d": false,
        "buyLink": null
    },
    {
        "date": "15.09",
        "time": "21:40",
        "filmId": "54590",
        "theatre": "Импульс",
        "cost": 350,
        "is3d": false,
        "buyLink": null
    },
    {
        "date": "18.09",
        "time": "14:00",
        "filmId": "54189",
        "theatre": "Импульс",
        "cost": 300,
        "is3d": false,
        "buyLink": null
    },
    {
        "date": "18.09",
        "time": "15:30",
        "filmId": "54538",
        "theatre": "Импульс",
        "cost": 300,
        "is3d": false,
        "buyLink": null
    },
    {
        "date": "18.09",
        "time": "19:10",
        "filmId": "54572",
        "theatre": "Импульс",
        "cost": 350,
        "is3d": false,
        "buyLink": null
    },
    {
        "date": "18.09",
        "time": "20:50",
        "filmId": "54573",
        "theatre": "Импульс",
        "cost": 350,
        "is3d": false,
        "buyLink": null
    }
]