[
    {
        "date": "25.01",
        "time": "21:05",
        "filmId": "avatar_fire_and_ash",
        "theatre": "8 планет",
        "cost": 600,
        "is3d": false,
        "buyLink": null
    },
    {
        "date": "25.01",
        "time": "21:25",
        "filmId": "avatar_fire_and_ash",
        "theatre": "8 планет ТЦ Клён",
        "cost": 700,
        "is3d": false,
        "buyLink": null
    },
    {
        "date": "25.01",
        "time": "21:25",
        "filmId": "return_to_silent_hill",
        "theatre": "8 планет",
        "cost": 500,
        "is3d": false,
        "buyLink": null
    },
    {
        "date": "25.01",
        "time": "21:40",
        "filmId": "the_rip",
        "theatre": "8 планет",
        "cost": 600,
        "is3d": false,
        "buyLink": null
    },
    {
        "date": "25.01",
        "time": "21:45",
        "filmId": "people_we_meet_on_vacation",
        "theatre": "8 планет",
        "cost": 600,
        "is3d": false,
        "buyLink": null
    },
    {
        "date": "25.01",
        "time": "21:50",
        "filmId": "levsha",
        "theatre": "8 планет",
        "cost": 500,
        "is3d": false,
        "buyLink": null
    },
    {
        "date": "25.01",
        "time": "21:55",
        "filmId": "levsha",
        "theatre": "8 планет",
        "cost": 1100,
        "is3d": false,
        "buyLink": null
    },
    {
        "date": "25.01",
        "time": "22:00",
        "filmId": "levsha",
        "theatre": "8 планет ТЦ Клён",
        "cost": 1100,
        "is3d": false,
        "buyLink": null
    },
    {
        "date": "25.01",
        "time": "22:05",
        "filmId": "the_housemaid",
        "theatre": "8 планет ТЦ Клён",
        "cost": 500,
        "is3d": false,
        "buyLink": null
    },
    {
        "date": "25.01",
        "time": "22:05",
        "filmId": "return_to_silent_hill",
        "theatre": "8 планет",
        "cost": 1100,
        "is3d": false,
        "buyLink": null
    },
    {
        "date": "25.01",
        "time": "22:30",
        "filmId": "return_to_silent_hill",
        "theatre": "8 планет ТЦ Клён",
        "cost": 500,
        "is3d": false,
        "buyLink": null
    },
    {
        "date": "26.01",
        "time": "10:20",
        "filmId": "levsha",
        "theatre": "8 планет",
        "cost": 300,
        "is3d": false,
        "buyLink": null
    },
    {
        "date": "26.01",
        "time": "10:20",
        "filmId": "cheburashka_2",
        "theatre": "8 планет ТЦ Клён",
        "cost": 300,
        "is3d": false,
        "buyLink": null
    },
    {
        "date": "26.01",
        "time": "10:25",
        "filmId": "69489",
        "theatre": "8 планет ТЦ Клён",
        "cost": 100,
        "is3d": false,
        "buyLink": null
    },
    {
        "date": "26.01",
        "time": "10:30",
        "filmId": "buratino",
        "theatre": "8 планет",
        "cost": 300,
        "is3d": false,
        "buyLink": null
    },
    {
        "date": "26.01",
        "time": "10:35",
        "filmId": "cheburashka_2",
        "theatre": "8 планет",
        "cost": 300,
        "is3d": false,
        "buyLink": null
    },
    {
        "date": "26.01",
        "time": "10:35",
        "filmId": "prostokvashino",
        "theatre": "8 планет",
        "cost": 300,
        "is3d": false,
        "buyLink": null
    },
    {
        "date": "26.01",
        "time": "10:40",
        "filmId": "69980",
        "theatre": "8 планет",
        "cost": 100,
        "is3d": false,
        "buyLink": null
    },
    {
        "date": "26.01",
        "time": "10:40",
        "filmId": "avatar_fire_and_ash",
        "theatre": "8 планет ТЦ Клён",
        "cost": 650,
        "is3d": false,
        "buyLink": null
    },
    {
        "date": "26.01",
        "time": "11:00",
        "filmId": "playdate",
        "theatre": "8 планет ТЦ Клён",
        "cost": 1000,
        "is3d": false,
        "buyLink": null
    },
    {
        "date": "26.01",
        "time": "11:35",
        "filmId": "prostokvashino",
        "theatre": "8 планет ТЦ Клён",
        "cost": 300,
        "is3d": false,
        "buyLink": null
    },
    {
        "date": "26.01",
        "time": "11:50",
        "filmId": "fleak_kekselias_ystavani",
        "theatre": "8 планет",
        "cost": 300,
        "is3d": false,
        "buyLink": null
    },
    {
        "date": "26.01",
        "time": "12:35",
        "filmId": "levsha",
        "theatre": "8 планет ТЦ Клён",
        "cost": 300,
        "is3d": false,
        "buyLink": null
    },
    {
        "date": "26.01",
        "time": "12:40",
        "filmId": "levsha",
        "theatre": "8 планет",
        "cost": 300,
        "is3d": false,
        "buyLink": null
    },
    {
        "date": "26.01",
        "time": "12:40",
        "filmId": "cheburashka_2",
        "theatre": "8 планет",
        "cost": 300,
        "is3d": false,
        "buyLink": null
    },
    {
        "date": "26.01",
        "time": "12:45",
        "filmId": "gabbys_dollhouse_the_movie",
        "theatre": "8 планет",
        "cost": 400,
        "is3d": false,
        "buyLink": null
    },
    {
        "date": "26.01",
        "time": "12:50",
        "filmId": "avatar_fire_and_ash",
        "theatre": "8 планет",
        "cost": 500,
        "is3d": false,
        "buyLink": null
    },
    {
        "date": "26.01",
        "time": "13:00",
        "filmId": "return_to_silent_hill",
        "theatre": "8 планет ТЦ Клён",
        "cost": 1000,
        "is3d": false,
        "buyLink": null
    },
    {
        "date": "26.01",
        "time": "13:40",
        "filmId": "zootopia_2",
        "theatre": "8 планет",
        "cost": 400,
        "is3d": false,
        "buyLink": null
    },
    {
        "date": "26.01",
        "time": "13:50",
        "filmId": "buratino",
        "theatre": "8 планет ТЦ Клён",
        "cost": 300,
        "is3d": false,
        "buyLink": null
    },
    {
        "date": "26.01",
        "time": "14:15",
        "filmId": "avatar_fire_and_ash",
        "theatre": "8 планет ТЦ Клён",
        "cost": 700,
        "is3d": false,
        "buyLink": null
    },
    {
        "date": "26.01",
        "time": "14:45",
        "filmId": "prostokvashino",
        "theatre": "8 планет",
        "cost": 400,
        "is3d": false,
        "buyLink": null
    },
    {
        "date": "26.01",
        "time": "14:55",
        "filmId": "buratino",
        "theatre": "8 планет",
        "cost": 400,
        "is3d": false,
        "buyLink": null
    },
    {
        "date": "26.01",
        "time": "15:00",
        "filmId": "levsha",
        "theatre": "8 планет ТЦ Клён",
        "cost": 400,
        "is3d": false,
        "buyLink": null
    },
    {
        "date": "26.01",
        "time": "15:00",
        "filmId": "return_to_silent_hill",
        "theatre": "8 планет",
        "cost": 400,
        "is3d": false,
        "buyLink": null
    },
    {
        "date": "26.01",
        "time": "15:10",
        "filmId": "playdate",
        "theatre": "8 планет ТЦ Клён",
        "cost": 1000,
        "is3d": false,
        "buyLink": null
    },
    {
        "date": "26.01",
        "time": "15:50",
        "filmId": "playdate",
        "theatre": "8 планет",
        "cost": 400,
        "is3d": false,
        "buyLink": null
    },
    {
        "date": "26.01",
        "time": "16:00",
        "filmId": "zootopia_2",
        "theatre": "8 планет ТЦ Клён",
        "cost": 500,
        "is3d": false,
        "buyLink": null
    },
    {
        "date": "26.01",
        "time": "16:30",
        "filmId": "avatar_fire_and_ash",
        "theatre": "8 планет",
        "cost": 550,
        "is3d": false,
        "buyLink": null
    },
    {
        "date": "26.01",
        "time": "17:00",
        "filmId": "return_to_silent_hill",
        "theatre": "8 планет",
        "cost": 400,
        "is3d": false,
        "buyLink": null
    },
    {
        "date": "26.01",
        "time": "17:05",
        "filmId": "cheburashka_2",
        "theatre": "8 планет",
        "cost": 400,
        "is3d": false,
        "buyLink": null
    },
    {
        "date": "26.01",
        "time": "17:10",
        "filmId": "levsha",
        "theatre": "8 планет",
        "cost": 400,
        "is3d": false,
        "buyLink": null
    },
    {
        "date": "26.01",
        "time": "17:10",
        "filmId": "return_to_silent_hill",
        "theatre": "8 планет ТЦ Клён",
        "cost": 1000,
        "is3d": false,
        "buyLink": null
    },
    {
        "date": "26.01",
        "time": "17:25",
        "filmId": "cheburashka_2",
        "theatre": "8 планет ТЦ Клён",
        "cost": 400,
        "is3d": false,
        "buyLink": null
    },
    {
        "date": "26.01",
        "time": "17:50",
        "filmId": "avatar_fire_and_ash",
        "theatre": "8 планет ТЦ Клён",
        "cost": 700,
        "is3d": false,
        "buyLink": null
    },
    {
        "date": "26.01",
        "time": "17:55",
        "filmId": "fleak_kekselias_ystavani",
        "theatre": "8 планет",
        "cost": 450,
        "is3d": false,
        "buyLink": null
    },
    {
        "date": "26.01",
        "time": "18:10",
        "filmId": "return_to_silent_hill",
        "theatre": "8 планет ТЦ Клён",
        "cost": 450,
        "is3d": false,
        "buyLink": null
    },
    {
        "date": "26.01",
        "time": "19:15",
        "filmId": "return_to_silent_hill",
        "theatre": "8 планет",
        "cost": 450,
        "is3d": false,
        "buyLink": null
    },
    {
        "date": "26.01",
        "time": "19:20",
        "filmId": "the_housemaid",
        "theatre": "8 планет ТЦ Клён",
        "cost": 1000,
        "is3d": false,
        "buyLink": null
    },
    {
        "date": "26.01",
        "time": "19:25",
        "filmId": "the_rip",
        "theatre": "8 планет",
        "cost": 550,
        "is3d": false,
        "buyLink": null
    },
    {
        "date": "26.01",
        "time": "19:30",
        "filmId": "levsha",
        "theatre": "8 планет",
        "cost": 450,
        "is3d": false,
        "buyLink": null
    },
    {
        "date": "26.01",
        "time": "19:40",
        "filmId": "levsha",
        "theatre": "8 планет ТЦ Клён",
        "cost": 450,
        "is3d": false,
        "buyLink": null
    },
    {
        "date": "26.01",
        "time": "19:45",
        "filmId": "playdate",
        "theatre": "8 планет",
        "cost": 450,
        "is3d": false,
        "buyLink": null
    },
    {
        "date": "26.01",
        "time": "20:10",
        "filmId": "avatar_fire_and_ash",
        "theatre": "8 планет",
        "cost": 550,
        "is3d": false,
        "buyLink": null
    },
    {
        "date": "26.01",
        "time": "20:20",
        "filmId": "return_to_silent_hill",
        "theatre": "8 планет ТЦ Клён",
        "cost": 450,
        "is3d": false,
        "buyLink": null
    },
    {
        "date": "26.01",
        "time": "21:25",
        "filmId": "avatar_fire_and_ash",
        "theatre": "8 планет ТЦ Клён",
        "cost": 700,
        "is3d": false,
        "buyLink": null
    },
    {
        "date": "26.01",
        "time": "21:25",
        "filmId": "return_to_silent_hill",
        "theatre": "8 планет",
        "cost": 450,
        "is3d": false,
        "buyLink": null
    },
    {
        "date": "26.01",
        "time": "21:40",
        "filmId": "the_rip",
        "theatre": "8 планет",
        "cost": 550,
        "is3d": false,
        "buyLink": null
    },
    {
        "date": "26.01",
        "time": "21:45",
        "filmId": "people_we_meet_on_vacation",
        "theatre": "8 планет",
        "cost": 550,
        "is3d": false,
        "buyLink": null
    },
    {
        "date": "26.01",
        "time": "21:50",
        "filmId": "levsha",
        "theatre": "8 планет",
        "cost": 450,
        "is3d": false,
        "buyLink": null
    },
    {
        "date": "26.01",
        "time": "22:00",
        "filmId": "levsha",
        "theatre": "8 планет ТЦ Клён",
        "cost": 1000,
        "is3d": false,
        "buyLink": null
    },
    {
        "date": "26.01",
        "time": "22:05",
        "filmId": "the_housemaid",
        "theatre": "8 планет ТЦ Клён",
        "cost": 450,
        "is3d": false,
        "buyLink": null
    },
    {
        "date": "26.01",
        "time": "22:30",
        "filmId": "return_to_silent_hill",
        "theatre": "8 планет ТЦ Клён",
        "cost": 450,
        "is3d": false,
        "buyLink": null
    },
    {
        "date": "27.01",
        "time": "10:20",
        "filmId": "levsha",
        "theatre": "8 планет",
        "cost": 300,
        "is3d": false,
        "buyLink": null
    },
    {
        "date": "27.01",
        "time": "10:20",
        "filmId": "cheburashka_2",
        "theatre": "8 планет ТЦ Клён",
        "cost": 300,
        "is3d": false,
        "buyLink": null
    },
    {
        "date": "27.01",
        "time": "10:25",
        "filmId": "69489",
        "theatre": "8 планет ТЦ Клён",
        "cost": 100,
        "is3d": false,
        "buyLink": null
    },
    {
        "date": "27.01",
        "time": "10:30",
        "filmId": "buratino",
        "theatre": "8 планет",
        "cost": 300,
        "is3d": false,
        "buyLink": null
    },
    {
        "date": "27.01",
        "time": "10:35",
        "filmId": "cheburashka_2",
        "theatre": "8 планет",
        "cost": 300,
        "is3d": false,
        "buyLink": null
    },
    {
        "date": "27.01",
        "time": "10:35",
        "filmId": "prostokvashino",
        "theatre": "8 планет",
        "cost": 300,
        "is3d": false,
        "buyLink": null
    },
    {
        "date": "27.01",
        "time": "10:40",
        "filmId": "69980",
        "theatre": "8 планет",
        "cost": 100,
        "is3d": false,
        "buyLink": null
    },
    {
        "date": "27.01",
        "time": "10:40",
        "filmId": "avatar_fire_and_ash",
        "theatre": "8 планет ТЦ Клён",
        "cost": 650,
        "is3d": false,
        "buyLink": null
    },
    {
        "date": "27.01",
        "time": "11:00",
        "filmId": "playdate",
        "theatre": "8 планет ТЦ Клён",
        "cost": 1000,
        "is3d": false,
        "buyLink": null
    },
    {
        "date": "27.01",
        "time": "11:35",
        "filmId": "prostokvashino",
        "theatre": "8 планет ТЦ Клён",
        "cost": 300,
        "is3d": false,
        "buyLink": null
    },
    {
        "date": "27.01",
        "time": "11:50",
        "filmId": "fleak_kekselias_ystavani",
        "theatre": "8 планет",
        "cost": 300,
        "is3d": false,
        "buyLink": null
    },
    {
        "date": "27.01",
        "time": "12:35",
        "filmId": "levsha",
        "theatre": "8 планет ТЦ Клён",
        "cost": 300,
        "is3d": false,
        "buyLink": null
    },
    {
        "date": "27.01",
        "time": "12:40",
        "filmId": "levsha",
        "theatre": "8 планет",
        "cost": 300,
        "is3d": false,
        "buyLink": null
    },
    {
        "date": "27.01",
        "time": "12:40",
        "filmId": "cheburashka_2",
        "theatre": "8 планет",
        "cost": 300,
        "is3d": false,
        "buyLink": null
    },
    {
        "date": "27.01",
        "time": "12:45",
        "filmId": "gabbys_dollhouse_the_movie",
        "theatre": "8 планет",
        "cost": 400,
        "is3d": false,
        "buyLink": null
    },
    {
        "date": "27.01",
        "time": "12:50",
        "filmId": "avatar_fire_and_ash",
        "theatre": "8 планет",
        "cost": 500,
        "is3d": false,
        "buyLink": null
    },
    {
        "date": "27.01",
        "time": "13:00",
        "filmId": "return_to_silent_hill",
        "theatre": "8 планет ТЦ Клён",
        "cost": 1000,
        "is3d": false,
        "buyLink": null
    },
    {
        "date": "27.01",
        "time": "13:40",
        "filmId": "zootopia_2",
        "theatre": "8 планет",
        "cost": 400,
        "is3d": false,
        "buyLink": null
    },
    {
        "date": "27.01",
        "time": "13:50",
        "filmId": "buratino",
        "theatre": "8 планет ТЦ Клён",
        "cost": 300,
        "is3d": false,
        "buyLink": null
    },
    {
        "date": "27.01",
        "time": "14:15",
        "filmId": "avatar_fire_and_ash",
        "theatre": "8 планет ТЦ Клён",
        "cost": 700,
        "is3d": false,
        "buyLink": null
    },
    {
        "date": "27.01",
        "time": "14:45",
        "filmId": "prostokvashino",
        "theatre": "8 планет",
        "cost": 400,
        "is3d": false,
        "buyLink": null
    },
    {
        "date": "27.01",
        "time": "14:55",
        "filmId": "buratino",
        "theatre": "8 планет",
        "cost": 400,
        "is3d": false,
        "buyLink": null
    },
    {
        "date": "27.01",
        "time": "15:00",
        "filmId": "levsha",
        "theatre": "8 планет ТЦ Клён",
        "cost": 400,
        "is3d": false,
        "buyLink": null
    },
    {
        "date": "27.01",
        "time": "15:00",
        "filmId": "return_to_silent_hill",
        "theatre": "8 планет",
        "cost": 400,
        "is3d": false,
        "buyLink": null
    },
    {
        "date": "27.01",
        "time": "15:10",
        "filmId": "playdate",
        "theatre": "8 планет ТЦ Клён",
        "cost": 1000,
        "is3d": false,
        "buyLink": null
    },
    {
        "date": "27.01",
        "time": "15:50",
        "filmId": "playdate",
        "theatre": "8 планет",
        "cost": 400,
        "is3d": false,
        "buyLink": null
    },
    {
        "date": "27.01",
        "time": "16:00",
        "filmId": "zootopia_2",
        "theatre": "8 планет ТЦ Клён",
        "cost": 500,
        "is3d": false,
        "buyLink": null
    },
    {
        "date": "27.01",
        "time": "16:30",
        "filmId": "avatar_fire_and_ash",
        "theatre": "8 планет",
        "cost": 550,
        "is3d": false,
        "buyLink": null
    },
    {
        "date": "27.01",
        "time": "17:00",
        "filmId": "return_to_silent_hill",
        "theatre": "8 планет",
        "cost": 400,
        "is3d": false,
        "buyLink": null
    },
    {
        "date": "27.01",
        "time": "17:05",
        "filmId": "cheburashka_2",
        "theatre": "8 планет",
        "cost": 400,
        "is3d": false,
        "buyLink": null
    },
    {
        "date": "27.01",
        "time": "17:10",
        "filmId": "levsha",
        "theatre": "8 планет",
        "cost": 400,
        "is3d": false,
        "buyLink": null
    },
    {
        "date": "27.01",
        "time": "17:10",
        "filmId": "return_to_silent_hill",
        "theatre": "8 планет ТЦ Клён",
        "cost": 1000,
        "is3d": false,
        "buyLink": null
    },
    {
        "date": "27.01",
        "time": "17:25",
        "filmId": "cheburashka_2",
        "theatre": "8 планет ТЦ Клён",
        "cost": 400,
        "is3d": false,
        "buyLink": null
    },
    {
        "date": "27.01",
        "time": "17:50",
        "filmId": "avatar_fire_and_ash",
        "theatre": "8 планет ТЦ Клён",
        "cost": 700,
        "is3d": false,
        "buyLink": null
    },
    {
        "date": "27.01",
        "time": "17:55",
        "filmId": "fleak_kekselias_ystavani",
        "theatre": "8 планет",
        "cost": 450,
        "is3d": false,
        "buyLink": null
    },
    {
        "date": "27.01",
        "time": "18:10",
        "filmId": "return_to_silent_hill",
        "theatre": "8 планет ТЦ Клён",
        "cost": 450,
        "is3d": false,
        "buyLink": null
    },
    {
        "date": "27.01",
        "time": "19:15",
        "filmId": "return_to_silent_hill",
        "theatre": "8 планет",
        "cost": 450,
        "is3d": false,
        "buyLink": null
    },
    {
        "date": "27.01",
        "time": "19:20",
        "filmId": "the_housemaid",
        "theatre": "8 планет ТЦ Клён",
        "cost": 1000,
        "is3d": false,
        "buyLink": null
    },
    {
        "date": "27.01",
        "time": "19:25",
        "filmId": "the_rip",
        "theatre": "8 планет",
        "cost": 550,
        "is3d": false,
        "buyLink": null
    },
    {
        "date": "27.01",
        "time": "19:30",
        "filmId": "levsha",
        "theatre": "8 планет",
        "cost": 450,
        "is3d": false,
        "buyLink": null
    },
    {
        "date": "27.01",
        "time": "19:40",
        "filmId": "levsha",
        "theatre": "8 планет ТЦ Клён",
        "cost": 450,
        "is3d": false,
        "buyLink": null
    },
    {
        "date": "27.01",
        "time": "19:45",
        "filmId": "playdate",
        "theatre": "8 планет",
        "cost": 450,
        "is3d": false,
        "buyLink": null
    },
    {
        "date": "27.01",
        "time": "20:10",
        "filmId": "avatar_fire_and_ash",
        "theatre": "8 планет",
        "cost": 550,
        "is3d": false,
        "buyLink": null
    },
    {
        "date": "27.01",
        "time": "20:20",
        "filmId": "return_to_silent_hill",
        "theatre": "8 планет ТЦ Клён",
        "cost": 450,
        "is3d": false,
        "buyLink": null
    },
    {
        "date": "27.01",
        "time": "21:25",
        "filmId": "avatar_fire_and_ash",
        "theatre": "8 планет ТЦ Клён",
        "cost": 700,
        "is3d": false,
        "buyLink": null
    },
    {
        "date": "27.01",
        "time": "21:25",
        "filmId": "return_to_silent_hill",
        "theatre": "8 планет",
        "cost": 450,
        "is3d": false,
        "buyLink": null
    },
    {
        "date": "27.01",
        "time": "21:40",
        "filmId": "the_rip",
        "theatre": "8 планет",
        "cost": 550,
        "is3d": false,
        "buyLink": null
    },
    {
        "date": "27.01",
        "time": "21:45",
        "filmId": "people_we_meet_on_vacation",
        "theatre": "8 планет",
        "cost": 550,
        "is3d": false,
        "buyLink": null
    },
    {
        "date": "27.01",
        "time": "21:50",
        "filmId": "levsha",
        "theatre": "8 планет",
        "cost": 450,
        "is3d": false,
        "buyLink": null
    },
    {
        "date": "27.01",
        "time": "22:00",
        "filmId": "levsha",
        "theatre": "8 планет ТЦ Клён",
        "cost": 1000,
        "is3d": false,
        "buyLink": null
    },
    {
        "date": "27.01",
        "time": "22:05",
        "filmId": "the_housemaid",
        "theatre": "8 планет ТЦ Клён",
        "cost": 450,
        "is3d": false,
        "buyLink": null
    },
    {
        "date": "27.01",
        "time": "22:30",
        "filmId": "return_to_silent_hill",
        "theatre": "8 планет ТЦ Клён",
        "cost": 450,
        "is3d": false,
        "buyLink": null
    },
    {
        "date": "28.01",
        "time": "10:20",
        "filmId": "levsha",
        "theatre": "8 планет",
        "cost": 300,
        "is3d": false,
        "buyLink": null
    },
    {
        "date": "28.01",
        "time": "10:20",
        "filmId": "cheburashka_2",
        "theatre": "8 планет ТЦ Клён",
        "cost": 300,
        "is3d": false,
        "buyLink": null
    },
    {
        "date": "28.01",
        "time": "10:25",
        "filmId": "69489",
        "theatre": "8 планет ТЦ Клён",
        "cost": 100,
        "is3d": false,
        "buyLink": null
    },
    {
        "date": "28.01",
        "time": "10:30",
        "filmId": "buratino",
        "theatre": "8 планет",
        "cost": 300,
        "is3d": false,
        "buyLink": null
    },
    {
        "date": "28.01",
        "time": "10:35",
        "filmId": "cheburashka_2",
        "theatre": "8 планет",
        "cost": 300,
        "is3d": false,
        "buyLink": null
    },
    {
        "date": "28.01",
        "time": "10:35",
        "filmId": "prostokvashino",
        "theatre": "8 планет",
        "cost": 300,
        "is3d": false,
        "buyLink": null
    },
    {
        "date": "28.01",
        "time": "10:40",
        "filmId": "69980",
        "theatre": "8 планет",
        "cost": 100,
        "is3d": false,
        "buyLink": null
    },
    {
        "date": "28.01",
        "time": "10:40",
        "filmId": "avatar_fire_and_ash",
        "theatre": "8 планет ТЦ Клён",
        "cost": 650,
        "is3d": false,
        "buyLink": null
    },
    {
        "date": "28.01",
        "time": "11:00",
        "filmId": "playdate",
        "theatre": "8 планет ТЦ Клён",
        "cost": 1000,
        "is3d": false,
        "buyLink": null
    },
    {
        "date": "28.01",
        "time": "11:35",
        "filmId": "prostokvashino",
        "theatre": "8 планет ТЦ Клён",
        "cost": 300,
        "is3d": false,
        "buyLink": null
    },
    {
        "date": "28.01",
        "time": "11:50",
        "filmId": "fleak_kekselias_ystavani",
        "theatre": "8 планет",
        "cost": 300,
        "is3d": false,
        "buyLink": null
    },
    {
        "date": "28.01",
        "time": "12:35",
        "filmId": "levsha",
        "theatre": "8 планет ТЦ Клён",
        "cost": 300,
        "is3d": false,
        "buyLink": null
    },
    {
        "date": "28.01",
        "time": "12:40",
        "filmId": "levsha",
        "theatre": "8 планет",
        "cost": 300,
        "is3d": false,
        "buyLink": null
    },
    {
        "date": "28.01",
        "time": "12:40",
        "filmId": "cheburashka_2",
        "theatre": "8 планет",
        "cost": 300,
        "is3d": false,
        "buyLink": null
    },
    {
        "date": "28.01",
        "time": "12:45",
        "filmId": "gabbys_dollhouse_the_movie",
        "theatre": "8 планет",
        "cost": 400,
        "is3d": false,
        "buyLink": null
    },
    {
        "date": "28.01",
        "time": "12:50",
        "filmId": "avatar_fire_and_ash",
        "theatre": "8 планет",
        "cost": 500,
        "is3d": false,
        "buyLink": null
    },
    {
        "date": "28.01",
        "time": "13:00",
        "filmId": "return_to_silent_hill",
        "theatre": "8 планет ТЦ Клён",
        "cost": 1000,
        "is3d": false,
        "buyLink": null
    },
    {
        "date": "28.01",
        "time": "13:40",
        "filmId": "zootopia_2",
        "theatre": "8 планет",
        "cost": 400,
        "is3d": false,
        "buyLink": null
    },
    {
        "date": "28.01",
        "time": "13:50",
        "filmId": "buratino",
        "theatre": "8 планет ТЦ Клён",
        "cost": 300,
        "is3d": false,
        "buyLink": null
    },
    {
        "date": "28.01",
        "time": "14:15",
        "filmId": "avatar_fire_and_ash",
        "theatre": "8 планет ТЦ Клён",
        "cost": 700,
        "is3d": false,
        "buyLink": null
    },
    {
        "date": "28.01",
        "time": "14:45",
        "filmId": "prostokvashino",
        "theatre": "8 планет",
        "cost": 400,
        "is3d": false,
        "buyLink": null
    },
    {
        "date": "28.01",
        "time": "14:55",
        "filmId": "buratino",
        "theatre": "8 планет",
        "cost": 400,
        "is3d": false,
        "buyLink": null
    },
    {
        "date": "28.01",
        "time": "15:00",
        "filmId": "levsha",
        "theatre": "8 планет ТЦ Клён",
        "cost": 400,
        "is3d": false,
        "buyLink": null
    },
    {
        "date": "28.01",
        "time": "15:00",
        "filmId": "return_to_silent_hill",
        "theatre": "8 планет",
        "cost": 400,
        "is3d": false,
        "buyLink": null
    },
    {
        "date": "28.01",
        "time": "15:10",
        "filmId": "playdate",
        "theatre": "8 планет ТЦ Клён",
        "cost": 1000,
        "is3d": false,
        "buyLink": null
    },
    {
        "date": "28.01",
        "time": "15:50",
        "filmId": "playdate",
        "theatre": "8 планет",
        "cost": 400,
        "is3d": false,
        "buyLink": null
    },
    {
        "date": "28.01",
        "time": "16:00",
        "filmId": "zootopia_2",
        "theatre": "8 планет ТЦ Клён",
        "cost": 500,
        "is3d": false,
        "buyLink": null
    },
    {
        "date": "28.01",
        "time": "16:30",
        "filmId": "avatar_fire_and_ash",
        "theatre": "8 планет",
        "cost": 550,
        "is3d": false,
        "buyLink": null
    },
    {
        "date": "28.01",
        "time": "17:00",
        "filmId": "return_to_silent_hill",
        "theatre": "8 планет",
        "cost": 400,
        "is3d": false,
        "buyLink": null
    },
    {
        "date": "28.01",
        "time": "17:05",
        "filmId": "cheburashka_2",
        "theatre": "8 планет",
        "cost": 400,
        "is3d": false,
        "buyLink": null
    },
    {
        "date": "28.01",
        "time": "17:10",
        "filmId": "levsha",
        "theatre": "8 планет",
        "cost": 400,
        "is3d": false,
        "buyLink": null
    },
    {
        "date": "28.01",
        "time": "17:10",
        "filmId": "return_to_silent_hill",
        "theatre": "8 планет ТЦ Клён",
        "cost": 1000,
        "is3d": false,
        "buyLink": null
    },
    {
        "date": "28.01",
        "time": "17:25",
        "filmId": "cheburashka_2",
        "theatre": "8 планет ТЦ Клён",
        "cost": 400,
        "is3d": false,
        "buyLink": null
    },
    {
        "date": "28.01",
        "time": "17:50",
        "filmId": "avatar_fire_and_ash",
        "theatre": "8 планет ТЦ Клён",
        "cost": 700,
        "is3d": false,
        "buyLink": null
    },
    {
        "date": "28.01",
        "time": "17:55",
        "filmId": "fleak_kekselias_ystavani",
        "theatre": "8 планет",
        "cost": 450,
        "is3d": false,
        "buyLink": null
    },
    {
        "date": "28.01",
        "time": "18:10",
        "filmId": "return_to_silent_hill",
        "theatre": "8 планет ТЦ Клён",
        "cost": 450,
        "is3d": false,
        "buyLink": null
    },
    {
        "date": "28.01",
        "time": "19:15",
        "filmId": "return_to_silent_hill",
        "theatre": "8 планет",
        "cost": 450,
        "is3d": false,
        "buyLink": null
    },
    {
        "date": "28.01",
        "time": "19:20",
        "filmId": "the_housemaid",
        "theatre": "8 планет ТЦ Клён",
        "cost": 1000,
        "is3d": false,
        "buyLink": null
    },
    {
        "date": "28.01",
        "time": "19:25",
        "filmId": "the_rip",
        "theatre": "8 планет",
        "cost": 550,
        "is3d": false,
        "buyLink": null
    },
    {
        "date": "28.01",
        "time": "19:30",
        "filmId": "levsha",
        "theatre": "8 планет",
        "cost": 450,
        "is3d": false,
        "buyLink": null
    },
    {
        "date": "28.01",
        "time": "19:40",
        "filmId": "levsha",
        "theatre": "8 планет ТЦ Клён",
        "cost": 450,
        "is3d": false,
        "buyLink": null
    },
    {
        "date": "28.01",
        "time": "19:45",
        "filmId": "playdate",
        "theatre": "8 планет",
        "cost": 450,
        "is3d": false,
        "buyLink": null
    },
    {
        "date": "28.01",
        "time": "20:10",
        "filmId": "avatar_fire_and_ash",
        "theatre": "8 планет",
        "cost": 550,
        "is3d": false,
        "buyLink": null
    },
    {
        "date": "28.01",
        "time": "20:20",
        "filmId": "return_to_silent_hill",
        "theatre": "8 планет ТЦ Клён",
        "cost": 450,
        "is3d": false,
        "buyLink": null
    },
    {
        "date": "28.01",
        "time": "21:25",
        "filmId": "avatar_fire_and_ash",
        "theatre": "8 планет ТЦ Клён",
        "cost": 700,
        "is3d": false,
        "buyLink": null
    },
    {
        "date": "28.01",
        "time": "21:25",
        "filmId": "return_to_silent_hill",
        "theatre": "8 планет",
        "cost": 450,
        "is3d": false,
        "buyLink": null
    },
    {
        "date": "28.01",
        "time": "21:40",
        "filmId": "the_rip",
        "theatre": "8 планет",
        "cost": 550,
        "is3d": false,
        "buyLink": null
    },
    {
        "date": "28.01",
        "time": "21:45",
        "filmId": "people_we_meet_on_vacation",
        "theatre": "8 планет",
        "cost": 550,
        "is3d": false,
        "buyLink": null
    },
    {
        "date": "28.01",
        "time": "21:50",
        "filmId": "levsha",
        "theatre": "8 планет",
        "cost": 450,
        "is3d": false,
        "buyLink": null
    },
    {
        "date": "28.01",
        "time": "22:00",
        "filmId": "levsha",
        "theatre": "8 планет ТЦ Клён",
        "cost": 1000,
        "is3d": false,
        "buyLink": null
    },
    {
        "date": "28.01",
        "time": "22:05",
        "filmId": "the_housemaid",
        "theatre": "8 планет ТЦ Клён",
        "cost": 450,
        "is3d": false,
        "buyLink": null
    },
    {
        "date": "28.01",
        "time": "22:30",
        "filmId": "return_to_silent_hill",
        "theatre": "8 планет ТЦ Клён",
        "cost": 450,
        "is3d": false,
        "buyLink": null
    }
]