[
    {
        "date": "10.09",
        "time": "09:40",
        "filmId": "doktor_dinozavrov",
        "theatre": "8 планет",
        "cost": 300,
        "is3d": false,
        "buyLink": null
    },
    {
        "date": "10.09",
        "time": "09:40",
        "filmId": "doktor_dinozavrov",
        "theatre": "8 планет ТЦ Клён",
        "cost": 300,
        "is3d": false,
        "buyLink": null
    },
    {
        "date": "10.09",
        "time": "09:40",
        "filmId": "65961",
        "theatre": "8 планет",
        "cost": 100,
        "is3d": false,
        "buyLink": null
    },
    {
        "date": "10.09",
        "time": "09:45",
        "filmId": "elio",
        "theatre": "8 планет",
        "cost": 400,
        "is3d": false,
        "buyLink": null
    },
    {
        "date": "10.09",
        "time": "09:45",
        "filmId": "kolbasa",
        "theatre": "8 планет ТЦ Клён",
        "cost": 300,
        "is3d": false,
        "buyLink": null
    },
    {
        "date": "10.09",
        "time": "09:50",
        "filmId": "the_bad_guys_2",
        "theatre": "8 планет",
        "cost": 400,
        "is3d": false,
        "buyLink": null
    },
    {
        "date": "10.09",
        "time": "10:00",
        "filmId": "semejnyj_prizrak",
        "theatre": "8 планет ТЦ Клён",
        "cost": 300,
        "is3d": false,
        "buyLink": null
    },
    {
        "date": "10.09",
        "time": "10:40",
        "filmId": "smurfs",
        "theatre": "8 планет",
        "cost": 400,
        "is3d": false,
        "buyLink": null
    },
    {
        "date": "10.09",
        "time": "11:10",
        "filmId": "the_toxic_avenger",
        "theatre": "8 планет ТЦ Клён",
        "cost": 1000,
        "is3d": false,
        "buyLink": null
    },
    {
        "date": "10.09",
        "time": "11:40",
        "filmId": "65961",
        "theatre": "8 планет ТЦ Клён",
        "cost": 100,
        "is3d": false,
        "buyLink": null
    },
    {
        "date": "10.09",
        "time": "11:45",
        "filmId": "skazki_temnogo_lesa_vorozheya",
        "theatre": "8 планет",
        "cost": 300,
        "is3d": false,
        "buyLink": null
    },
    {
        "date": "10.09",
        "time": "11:45",
        "filmId": "jurassic_world_rebirth",
        "theatre": "8 планет",
        "cost": 400,
        "is3d": false,
        "buyLink": null
    },
    {
        "date": "10.09",
        "time": "11:50",
        "filmId": "deti_shpiony",
        "theatre": "8 планет ТЦ Клён",
        "cost": 300,
        "is3d": false,
        "buyLink": null
    },
    {
        "date": "10.09",
        "time": "11:55",
        "filmId": "vniz",
        "theatre": "8 планет ТЦ Клён",
        "cost": 300,
        "is3d": false,
        "buyLink": null
    },
    {
        "date": "10.09",
        "time": "11:55",
        "filmId": "61947",
        "theatre": "8 планет",
        "cost": 400,
        "is3d": false,
        "buyLink": null
    },
    {
        "date": "10.09",
        "time": "12:30",
        "filmId": "vniz",
        "theatre": "8 планет",
        "cost": 300,
        "is3d": false,
        "buyLink": null
    },
    {
        "date": "10.09",
        "time": "12:45",
        "filmId": "doktor_dinozavrov",
        "theatre": "8 планет ТЦ Клён",
        "cost": 300,
        "is3d": false,
        "buyLink": null
    },
    {
        "date": "10.09",
        "time": "13:20",
        "filmId": "65752",
        "theatre": "8 планет ТЦ Клён",
        "cost": 1000,
        "is3d": false,
        "buyLink": null
    },
    {
        "date": "10.09",
        "time": "13:40",
        "filmId": "the_toxic_avenger",
        "theatre": "8 планет",
        "cost": 300,
        "is3d": false,
        "buyLink": null
    },
    {
        "date": "10.09",
        "time": "13:45",
        "filmId": "ritmy_mechty",
        "theatre": "8 планет ТЦ Клён",
        "cost": 300,
        "is3d": false,
        "buyLink": null
    },
    {
        "date": "10.09",
        "time": "13:55",
        "filmId": "semejnyj_prizrak",
        "theatre": "8 планет ТЦ Клён",
        "cost": 400,
        "is3d": false,
        "buyLink": null
    },
    {
        "date": "10.09",
        "time": "14:05",
        "filmId": "caught_stealing",
        "theatre": "8 планет",
        "cost": 500,
        "is3d": false,
        "buyLink": null
    },
    {
        "date": "10.09",
        "time": "14:25",
        "filmId": "doktor_dinozavrov",
        "theatre": "8 планет",
        "cost": 400,
        "is3d": false,
        "buyLink": null
    },
    {
        "date": "10.09",
        "time": "14:30",
        "filmId": "vniz",
        "theatre": "8 планет",
        "cost": 400,
        "is3d": false,
        "buyLink": null
    },
    {
        "date": "10.09",
        "time": "14:45",
        "filmId": "identifikacija_2025",
        "theatre": "8 планет ТЦ Клён",
        "cost": 400,
        "is3d": false,
        "buyLink": null
    },
    {
        "date": "10.09",
        "time": "15:40",
        "filmId": "witchboard",
        "theatre": "8 планет ТЦ Клён",
        "cost": 1000,
        "is3d": false,
        "buyLink": null
    },
    {
        "date": "10.09",
        "time": "15:50",
        "filmId": "vniz",
        "theatre": "8 планет ТЦ Клён",
        "cost": 400,
        "is3d": false,
        "buyLink": null
    },
    {
        "date": "10.09",
        "time": "15:50",
        "filmId": "the_toxic_avenger",
        "theatre": "8 планет",
        "cost": 400,
        "is3d": false,
        "buyLink": null
    },
    {
        "date": "10.09",
        "time": "15:55",
        "filmId": "kolbasa",
        "theatre": "8 планет ТЦ Клён",
        "cost": 400,
        "is3d": false,
        "buyLink": null
    },
    {
        "date": "10.09",
        "time": "16:10",
        "filmId": "the_cut",
        "theatre": "8 планет",
        "cost": 400,
        "is3d": false,
        "buyLink": null
    },
    {
        "date": "10.09",
        "time": "16:25",
        "filmId": "doktor_dinozavrov",
        "theatre": "8 планет",
        "cost": 400,
        "is3d": false,
        "buyLink": null
    },
    {
        "date": "10.09",
        "time": "16:30",
        "filmId": "vniz",
        "theatre": "8 планет",
        "cost": 400,
        "is3d": false,
        "buyLink": null
    },
    {
        "date": "10.09",
        "time": "16:35",
        "filmId": "doktor_dinozavrov",
        "theatre": "8 планет ТЦ Клён",
        "cost": 400,
        "is3d": false,
        "buyLink": null
    },
    {
        "date": "10.09",
        "time": "17:50",
        "filmId": "vniz",
        "theatre": "8 планет ТЦ Клён",
        "cost": 450,
        "is3d": false,
        "buyLink": null
    },
    {
        "date": "10.09",
        "time": "18:00",
        "filmId": "deti_shpiony",
        "theatre": "8 планет ТЦ Клён",
        "cost": 450,
        "is3d": false,
        "buyLink": null
    },
    {
        "date": "10.09",
        "time": "18:00",
        "filmId": "semejnyj_prizrak",
        "theatre": "8 планет ТЦ Клён",
        "cost": 1000,
        "is3d": false,
        "buyLink": null
    },
    {
        "date": "10.09",
        "time": "18:00",
        "filmId": "freakier_friday",
        "theatre": "8 планет",
        "cost": 550,
        "is3d": false,
        "buyLink": null
    },
    {
        "date": "10.09",
        "time": "18:15",
        "filmId": "jeokjijeok_dokja_sijeom",
        "theatre": "8 планет",
        "cost": 450,
        "is3d": false,
        "buyLink": null
    },
    {
        "date": "10.09",
        "time": "18:25",
        "filmId": "semejnyj_prizrak",
        "theatre": "8 планет",
        "cost": 450,
        "is3d": false,
        "buyLink": null
    },
    {
        "date": "10.09",
        "time": "18:30",
        "filmId": "vniz",
        "theatre": "8 планет",
        "cost": 450,
        "is3d": false,
        "buyLink": null
    },
    {
        "date": "10.09",
        "time": "18:35",
        "filmId": "the_toxic_avenger",
        "theatre": "8 планет ТЦ Клён",
        "cost": 450,
        "is3d": false,
        "buyLink": null
    },
    {
        "date": "10.09",
        "time": "19:50",
        "filmId": "vniz",
        "theatre": "8 планет ТЦ Клён",
        "cost": 450,
        "is3d": false,
        "buyLink": null
    },
    {
        "date": "10.09",
        "time": "19:55",
        "filmId": "kolbasa",
        "theatre": "8 планет ТЦ Клён",
        "cost": 450,
        "is3d": false,
        "buyLink": null
    },
    {
        "date": "10.09",
        "time": "19:55",
        "filmId": "jugaremos_en_el_bosque",
        "theatre": "8 планет ТЦ Клён",
        "cost": 1000,
        "is3d": false,
        "buyLink": null
    },
    {
        "date": "10.09",
        "time": "20:15",
        "filmId": "vniz",
        "theatre": "8 планет",
        "cost": 450,
        "is3d": false,
        "buyLink": null
    },
    {
        "date": "10.09",
        "time": "20:20",
        "filmId": "65627",
        "theatre": "8 планет",
        "cost": 450,
        "is3d": false,
        "buyLink": null
    },
    {
        "date": "10.09",
        "time": "20:30",
        "filmId": "65643",
        "theatre": "8 планет",
        "cost": 550,
        "is3d": false,
        "buyLink": null
    },
    {
        "date": "10.09",
        "time": "20:40",
        "filmId": "8ban_deguchi",
        "theatre": "8 планет ТЦ Клён",
        "cost": 450,
        "is3d": false,
        "buyLink": null
    },
    {
        "date": "10.09",
        "time": "20:40",
        "filmId": "caught_stealing",
        "theatre": "8 планет",
        "cost": 550,
        "is3d": false,
        "buyLink": null
    },
    {
        "date": "10.09",
        "time": "21:50",
        "filmId": "witchboard",
        "theatre": "8 планет ТЦ Клён",
        "cost": 450,
        "is3d": false,
        "buyLink": null
    },
    {
        "date": "10.09",
        "time": "22:00",
        "filmId": "vniz",
        "theatre": "8 планет ТЦ Клён",
        "cost": 1000,
        "is3d": false,
        "buyLink": null
    },
    {
        "date": "10.09",
        "time": "22:00",
        "filmId": "jugaremos_en_el_bosque",
        "theatre": "8 планет ТЦ Клён",
        "cost": 450,
        "is3d": false,
        "buyLink": null
    },
    {
        "date": "10.09",
        "time": "22:10",
        "filmId": "63162",
        "theatre": "8 планет",
        "cost": 550,
        "is3d": false,
        "buyLink": null
    },
    {
        "date": "10.09",
        "time": "22:20",
        "filmId": "the_toxic_avenger",
        "theatre": "8 планет",
        "cost": 450,
        "is3d": false,
        "buyLink": null
    },
    {
        "date": "10.09",
        "time": "22:35",
        "filmId": "weapons",
        "theatre": "8 планет",
        "cost": 550,
        "is3d": false,
        "buyLink": null
    },
    {
        "date": "10.09",
        "time": "22:40",
        "filmId": "the_toxic_avenger",
        "theatre": "8 планет ТЦ Клён",
        "cost": 450,
        "is3d": false,
        "buyLink": null
    },
    {
        "date": "10.09",
        "time": "22:50",
        "filmId": "caught_stealing",
        "theatre": "8 планет",
        "cost": 550,
        "is3d": false,
        "buyLink": null
    },
    {
        "date": "11.09",
        "time": "10:30",
        "filmId": "begi",
        "theatre": "8 планет ТЦ Клён",
        "cost": 300,
        "is3d": false,
        "buyLink": null
    },
    {
        "date": "11.09",
        "time": "10:35",
        "filmId": "vniz",
        "theatre": "8 планет ТЦ Клён",
        "cost": 300,
        "is3d": false,
        "buyLink": null
    },
    {
        "date": "11.09",
        "time": "10:40",
        "filmId": "falcon_express",
        "theatre": "8 планет ТЦ Клён",
        "cost": 300,
        "is3d": false,
        "buyLink": null
    },
    {
        "date": "11.09",
        "time": "12:20",
        "filmId": "kolbasa",
        "theatre": "8 планет ТЦ Клён",
        "cost": 300,
        "is3d": false,
        "buyLink": null
    },
    {
        "date": "11.09",
        "time": "12:30",
        "filmId": "doktor_dinozavrov",
        "theatre": "8 планет ТЦ Клён",
        "cost": 300,
        "is3d": false,
        "buyLink": null
    },
    {
        "date": "11.09",
        "time": "12:35",
        "filmId": "65961",
        "theatre": "8 планет ТЦ Клён",
        "cost": 100,
        "is3d": false,
        "buyLink": null
    },
    {
        "date": "11.09",
        "time": "13:40",
        "filmId": "the_toxic_avenger",
        "theatre": "8 планет ТЦ Клён",
        "cost": 300,
        "is3d": false,
        "buyLink": null
    },
    {
        "date": "11.09",
        "time": "14:25",
        "filmId": "begi",
        "theatre": "8 планет ТЦ Клён",
        "cost": 400,
        "is3d": false,
        "buyLink": null
    },
    {
        "date": "11.09",
        "time": "14:30",
        "filmId": "dracula_a_love_tale",
        "theatre": "8 планет ТЦ Клён",
        "cost": 400,
        "is3d": false,
        "buyLink": null
    },
    {
        "date": "11.09",
        "time": "15:50",
        "filmId": "vniz",
        "theatre": "8 планет ТЦ Клён",
        "cost": 400,
        "is3d": false,
        "buyLink": null
    },
    {
        "date": "11.09",
        "time": "16:20",
        "filmId": "semejnyj_prizrak",
        "theatre": "8 планет ТЦ Клён",
        "cost": 400,
        "is3d": false,
        "buyLink": null
    },
    {
        "date": "11.09",
        "time": "16:50",
        "filmId": "dracula_a_love_tale",
        "theatre": "8 планет ТЦ Клён",
        "cost": 1000,
        "is3d": false,
        "buyLink": null
    },
    {
        "date": "11.09",
        "time": "17:05",
        "filmId": "falcon_express",
        "theatre": "8 планет ТЦ Клён",
        "cost": 400,
        "is3d": false,
        "buyLink": null
    },
    {
        "date": "11.09",
        "time": "17:50",
        "filmId": "doktor_dinozavrov",
        "theatre": "8 планет ТЦ Клён",
        "cost": 450,
        "is3d": false,
        "buyLink": null
    },
    {
        "date": "11.09",
        "time": "18:20",
        "filmId": "begi",
        "theatre": "8 планет ТЦ Клён",
        "cost": 450,
        "is3d": false,
        "buyLink": null
    },
    {
        "date": "11.09",
        "time": "19:00",
        "filmId": "dracula_a_love_tale",
        "theatre": "8 планет ТЦ Клён",
        "cost": 450,
        "is3d": false,
        "buyLink": null
    },
    {
        "date": "11.09",
        "time": "19:30",
        "filmId": "begi",
        "theatre": "8 планет ТЦ Клён",
        "cost": 1000,
        "is3d": false,
        "buyLink": null
    },
    {
        "date": "11.09",
        "time": "19:55",
        "filmId": "8ban_deguchi",
        "theatre": "8 планет ТЦ Клён",
        "cost": 450,
        "is3d": false,
        "buyLink": null
    },
    {
        "date": "11.09",
        "time": "20:15",
        "filmId": "somnium",
        "theatre": "8 планет ТЦ Клён",
        "cost": 450,
        "is3d": false,
        "buyLink": null
    },
    {
        "date": "11.09",
        "time": "21:25",
        "filmId": "nan_jing_zhao_xiang_guan",
        "theatre": "8 планет ТЦ Клён",
        "cost": 1000,
        "is3d": false,
        "buyLink": null
    },
    {
        "date": "11.09",
        "time": "21:35",
        "filmId": "dracula_a_love_tale",
        "theatre": "8 планет ТЦ Клён",
        "cost": 450,
        "is3d": false,
        "buyLink": null
    },
    {
        "date": "11.09",
        "time": "22:00",
        "filmId": "vniz",
        "theatre": "8 планет ТЦ Клён",
        "cost": 450,
        "is3d": false,
        "buyLink": null
    },
    {
        "date": "11.09",
        "time": "22:10",
        "filmId": "jugaremos_en_el_bosque",
        "theatre": "8 планет ТЦ Клён",
        "cost": 450,
        "is3d": false,
        "buyLink": null
    },
    {
        "date": "12.09",
        "time": "10:30",
        "filmId": "begi",
        "theatre": "8 планет ТЦ Клён",
        "cost": 300,
        "is3d": false,
        "buyLink": null
    },
    {
        "date": "12.09",
        "time": "10:35",
        "filmId": "vniz",
        "theatre": "8 планет ТЦ Клён",
        "cost": 300,
        "is3d": false,
        "buyLink": null
    },
    {
        "date": "12.09",
        "time": "10:40",
        "filmId": "falcon_express",
        "theatre": "8 планет ТЦ Клён",
        "cost": 300,
        "is3d": false,
        "buyLink": null
    },
    {
        "date": "12.09",
        "time": "12:20",
        "filmId": "kolbasa",
        "theatre": "8 планет ТЦ Клён",
        "cost": 300,
        "is3d": false,
        "buyLink": null
    },
    {
        "date": "12.09",
        "time": "12:30",
        "filmId": "doktor_dinozavrov",
        "theatre": "8 планет ТЦ Клён",
        "cost": 300,
        "is3d": false,
        "buyLink": null
    },
    {
        "date": "12.09",
        "time": "12:35",
        "filmId": "65961",
        "theatre": "8 планет ТЦ Клён",
        "cost": 100,
        "is3d": false,
        "buyLink": null
    },
    {
        "date": "12.09",
        "time": "13:40",
        "filmId": "the_toxic_avenger",
        "theatre": "8 планет ТЦ Клён",
        "cost": 300,
        "is3d": false,
        "buyLink": null
    },
    {
        "date": "12.09",
        "time": "14:25",
        "filmId": "begi",
        "theatre": "8 планет ТЦ Клён",
        "cost": 400,
        "is3d": false,
        "buyLink": null
    },
    {
        "date": "12.09",
        "time": "14:30",
        "filmId": "dracula_a_love_tale",
        "theatre": "8 планет ТЦ Клён",
        "cost": 400,
        "is3d": false,
        "buyLink": null
    },
    {
        "date": "12.09",
        "time": "15:50",
        "filmId": "vniz",
        "theatre": "8 планет ТЦ Клён",
        "cost": 400,
        "is3d": false,
        "buyLink": null
    },
    {
        "date": "12.09",
        "time": "16:20",
        "filmId": "semejnyj_prizrak",
        "theatre": "8 планет ТЦ Клён",
        "cost": 400,
        "is3d": false,
        "buyLink": null
    },
    {
        "date": "12.09",
        "time": "16:50",
        "filmId": "dracula_a_love_tale",
        "theatre": "8 планет ТЦ Клён",
        "cost": 1000,
        "is3d": false,
        "buyLink": null
    },
    {
        "date": "12.09",
        "time": "17:05",
        "filmId": "falcon_express",
        "theatre": "8 планет ТЦ Клён",
        "cost": 400,
        "is3d": false,
        "buyLink": null
    },
    {
        "date": "12.09",
        "time": "17:50",
        "filmId": "doktor_dinozavrov",
        "theatre": "8 планет ТЦ Клён",
        "cost": 470,
        "is3d": false,
        "buyLink": null
    },
    {
        "date": "12.09",
        "time": "18:20",
        "filmId": "begi",
        "theatre": "8 планет ТЦ Клён",
        "cost": 470,
        "is3d": false,
        "buyLink": null
    },
    {
        "date": "12.09",
        "time": "19:00",
        "filmId": "dracula_a_love_tale",
        "theatre": "8 планет ТЦ Клён",
        "cost": 470,
        "is3d": false,
        "buyLink": null
    },
    {
        "date": "12.09",
        "time": "19:30",
        "filmId": "begi",
        "theatre": "8 планет ТЦ Клён",
        "cost": 1000,
        "is3d": false,
        "buyLink": null
    },
    {
        "date": "12.09",
        "time": "19:55",
        "filmId": "8ban_deguchi",
        "theatre": "8 планет ТЦ Клён",
        "cost": 470,
        "is3d": false,
        "buyLink": null
    },
    {
        "date": "12.09",
        "time": "20:15",
        "filmId": "somnium",
        "theatre": "8 планет ТЦ Клён",
        "cost": 470,
        "is3d": false,
        "buyLink": null
    },
    {
        "date": "12.09",
        "time": "21:25",
        "filmId": "nan_jing_zhao_xiang_guan",
        "theatre": "8 планет ТЦ Клён",
        "cost": 1000,
        "is3d": false,
        "buyLink": null
    },
    {
        "date": "12.09",
        "time": "21:35",
        "filmId": "dracula_a_love_tale",
        "theatre": "8 планет ТЦ Клён",
        "cost": 470,
        "is3d": false,
        "buyLink": null
    },
    {
        "date": "12.09",
        "time": "22:00",
        "filmId": "vniz",
        "theatre": "8 планет ТЦ Клён",
        "cost": 470,
        "is3d": false,
        "buyLink": null
    },
    {
        "date": "12.09",
        "time": "22:10",
        "filmId": "jugaremos_en_el_bosque",
        "theatre": "8 планет ТЦ Клён",
        "cost": 470,
        "is3d": false,
        "buyLink": null
    },
    {
        "date": "13.09",
        "time": "10:30",
        "filmId": "begi",
        "theatre": "8 планет ТЦ Клён",
        "cost": 350,
        "is3d": false,
        "buyLink": null
    },
    {
        "date": "13.09",
        "time": "10:35",
        "filmId": "vniz",
        "theatre": "8 планет ТЦ Клён",
        "cost": 350,
        "is3d": false,
        "buyLink": null
    },
    {
        "date": "13.09",
        "time": "10:40",
        "filmId": "falcon_express",
        "theatre": "8 планет ТЦ Клён",
        "cost": 350,
        "is3d": false,
        "buyLink": null
    },
    {
        "date": "13.09",
        "time": "12:10",
        "filmId": "dracula_a_love_tale",
        "theatre": "8 планет ТЦ Клён",
        "cost": 1100,
        "is3d": false,
        "buyLink": null
    },
    {
        "date": "13.09",
        "time": "12:20",
        "filmId": "kolbasa",
        "theatre": "8 планет ТЦ Клён",
        "cost": 370,
        "is3d": false,
        "buyLink": null
    },
    {
        "date": "13.09",
        "time": "12:30",
        "filmId": "doktor_dinozavrov",
        "theatre": "8 планет ТЦ Клён",
        "cost": 370,
        "is3d": false,
        "buyLink": null
    },
    {
        "date": "13.09",
        "time": "12:35",
        "filmId": "65961",
        "theatre": "8 планет ТЦ Клён",
        "cost": 100,
        "is3d": false,
        "buyLink": null
    },
    {
        "date": "13.09",
        "time": "13:40",
        "filmId": "the_toxic_avenger",
        "theatre": "8 планет ТЦ Клён",
        "cost": 370,
        "is3d": false,
        "buyLink": null
    },
    {
        "date": "13.09",
        "time": "14:25",
        "filmId": "begi",
        "theatre": "8 планет ТЦ Клён",
        "cost": 470,
        "is3d": false,
        "buyLink": null
    },
    {
        "date": "13.09",
        "time": "14:30",
        "filmId": "dracula_a_love_tale",
        "theatre": "8 планет ТЦ Клён",
        "cost": 470,
        "is3d": false,
        "buyLink": null
    },
    {
        "date": "13.09",
        "time": "14:50",
        "filmId": "falcon_express",
        "theatre": "8 планет ТЦ Клён",
        "cost": 1100,
        "is3d": false,
        "buyLink": null
    },
    {
        "date": "13.09",
        "time": "15:50",
        "filmId": "vniz",
        "theatre": "8 планет ТЦ Клён",
        "cost": 470,
        "is3d": false,
        "buyLink": null
    },
    {
        "date": "13.09",
        "time": "16:20",
        "filmId": "semejnyj_prizrak",
        "theatre": "8 планет ТЦ Клён",
        "cost": 470,
        "is3d": false,
        "buyLink": null
    },
    {
        "date": "13.09",
        "time": "16:50",
        "filmId": "dracula_a_love_tale",
        "theatre": "8 планет ТЦ Клён",
        "cost": 1100,
        "is3d": false,
        "buyLink": null
    },
    {
        "date": "13.09",
        "time": "17:05",
        "filmId": "falcon_express",
        "theatre": "8 планет ТЦ Клён",
        "cost": 470,
        "is3d": false,
        "buyLink": null
    },
    {
        "date": "13.09",
        "time": "17:50",
        "filmId": "doktor_dinozavrov",
        "theatre": "8 планет ТЦ Клён",
        "cost": 500,
        "is3d": false,
        "buyLink": null
    },
    {
        "date": "13.09",
        "time": "18:20",
        "filmId": "begi",
        "theatre": "8 планет ТЦ Клён",
        "cost": 500,
        "is3d": false,
        "buyLink": null
    },
    {
        "date": "13.09",
        "time": "19:00",
        "filmId": "dracula_a_love_tale",
        "theatre": "8 планет ТЦ Клён",
        "cost": 500,
        "is3d": false,
        "buyLink": null
    },
    {
        "date": "13.09",
        "time": "19:30",
        "filmId": "begi",
        "theatre": "8 планет ТЦ Клён",
        "cost": 1100,
        "is3d": false,
        "buyLink": null
    },
    {
        "date": "13.09",
        "time": "19:55",
        "filmId": "8ban_deguchi",
        "theatre": "8 планет ТЦ Клён",
        "cost": 500,
        "is3d": false,
        "buyLink": null
    },
    {
        "date": "13.09",
        "time": "20:15",
        "filmId": "somnium",
        "theatre": "8 планет ТЦ Клён",
        "cost": 500,
        "is3d": false,
        "buyLink": null
    },
    {
        "date": "13.09",
        "time": "21:25",
        "filmId": "nan_jing_zhao_xiang_guan",
        "theatre": "8 планет ТЦ Клён",
        "cost": 1100,
        "is3d": false,
        "buyLink": null
    },
    {
        "date": "13.09",
        "time": "21:35",
        "filmId": "dracula_a_love_tale",
        "theatre": "8 планет ТЦ Клён",
        "cost": 500,
        "is3d": false,
        "buyLink": null
    },
    {
        "date": "13.09",
        "time": "22:00",
        "filmId": "vniz",
        "theatre": "8 планет ТЦ Клён",
        "cost": 500,
        "is3d": false,
        "buyLink": null
    },
    {
        "date": "13.09",
        "time": "22:10",
        "filmId": "jugaremos_en_el_bosque",
        "theatre": "8 планет ТЦ Клён",
        "cost": 500,
        "is3d": false,
        "buyLink": null
    },
    {
        "date": "14.09",
        "time": "10:30",
        "filmId": "begi",
        "theatre": "8 планет ТЦ Клён",
        "cost": 350,
        "is3d": false,
        "buyLink": null
    },
    {
        "date": "14.09",
        "time": "10:35",
        "filmId": "vniz",
        "theatre": "8 планет ТЦ Клён",
        "cost": 350,
        "is3d": false,
        "buyLink": null
    },
    {
        "date": "14.09",
        "time": "10:40",
        "filmId": "falcon_express",
        "theatre": "8 планет ТЦ Клён",
        "cost": 350,
        "is3d": false,
        "buyLink": null
    },
    {
        "date": "14.09",
        "time": "12:10",
        "filmId": "dracula_a_love_tale",
        "theatre": "8 планет ТЦ Клён",
        "cost": 1100,
        "is3d": false,
        "buyLink": null
    },
    {
        "date": "14.09",
        "time": "12:20",
        "filmId": "kolbasa",
        "theatre": "8 планет ТЦ Клён",
        "cost": 370,
        "is3d": false,
        "buyLink": null
    },
    {
        "date": "14.09",
        "time": "12:30",
        "filmId": "doktor_dinozavrov",
        "theatre": "8 планет ТЦ Клён",
        "cost": 370,
        "is3d": false,
        "buyLink": null
    },
    {
        "date": "14.09",
        "time": "12:35",
        "filmId": "65961",
        "theatre": "8 планет ТЦ Клён",
        "cost": 100,
        "is3d": false,
        "buyLink": null
    },
    {
        "date": "14.09",
        "time": "13:40",
        "filmId": "the_toxic_avenger",
        "theatre": "8 планет ТЦ Клён",
        "cost": 370,
        "is3d": false,
        "buyLink": null
    },
    {
        "date": "14.09",
        "time": "14:25",
        "filmId": "begi",
        "theatre": "8 планет ТЦ Клён",
        "cost": 470,
        "is3d": false,
        "buyLink": null
    },
    {
        "date": "14.09",
        "time": "14:30",
        "filmId": "dracula_a_love_tale",
        "theatre": "8 планет ТЦ Клён",
        "cost": 470,
        "is3d": false,
        "buyLink": null
    },
    {
        "date": "14.09",
        "time": "14:50",
        "filmId": "falcon_express",
        "theatre": "8 планет ТЦ Клён",
        "cost": 1100,
        "is3d": false,
        "buyLink": null
    },
    {
        "date": "14.09",
        "time": "15:50",
        "filmId": "vniz",
        "theatre": "8 планет ТЦ Клён",
        "cost": 470,
        "is3d": false,
        "buyLink": null
    },
    {
        "date": "14.09",
        "time": "16:20",
        "filmId": "semejnyj_prizrak",
        "theatre": "8 планет ТЦ Клён",
        "cost": 470,
        "is3d": false,
        "buyLink": null
    },
    {
        "date": "14.09",
        "time": "16:50",
        "filmId": "dracula_a_love_tale",
        "theatre": "8 планет ТЦ Клён",
        "cost": 1100,
        "is3d": false,
        "buyLink": null
    },
    {
        "date": "14.09",
        "time": "17:05",
        "filmId": "falcon_express",
        "theatre": "8 планет ТЦ Клён",
        "cost": 470,
        "is3d": false,
        "buyLink": null
    },
    {
        "date": "14.09",
        "time": "17:50",
        "filmId": "doktor_dinozavrov",
        "theatre": "8 планет ТЦ Клён",
        "cost": 500,
        "is3d": false,
        "buyLink": null
    },
    {
        "date": "14.09",
        "time": "18:20",
        "filmId": "begi",
        "theatre": "8 планет ТЦ Клён",
        "cost": 500,
        "is3d": false,
        "buyLink": null
    },
    {
        "date": "14.09",
        "time": "19:00",
        "filmId": "dracula_a_love_tale",
        "theatre": "8 планет ТЦ Клён",
        "cost": 500,
        "is3d": false,
        "buyLink": null
    },
    {
        "date": "14.09",
        "time": "19:30",
        "filmId": "begi",
        "theatre": "8 планет ТЦ Клён",
        "cost": 1100,
        "is3d": false,
        "buyLink": null
    },
    {
        "date": "14.09",
        "time": "19:55",
        "filmId": "8ban_deguchi",
        "theatre": "8 планет ТЦ Клён",
        "cost": 500,
        "is3d": false,
        "buyLink": null
    },
    {
        "date": "14.09",
        "time": "20:15",
        "filmId": "somnium",
        "theatre": "8 планет ТЦ Клён",
        "cost": 500,
        "is3d": false,
        "buyLink": null
    },
    {
        "date": "14.09",
        "time": "21:25",
        "filmId": "nan_jing_zhao_xiang_guan",
        "theatre": "8 планет ТЦ Клён",
        "cost": 1100,
        "is3d": false,
        "buyLink": null
    },
    {
        "date": "14.09",
        "time": "21:35",
        "filmId": "dracula_a_love_tale",
        "theatre": "8 планет ТЦ Клён",
        "cost": 500,
        "is3d": false,
        "buyLink": null
    },
    {
        "date": "14.09",
        "time": "22:00",
        "filmId": "vniz",
        "theatre": "8 планет ТЦ Клён",
        "cost": 500,
        "is3d": false,
        "buyLink": null
    },
    {
        "date": "14.09",
        "time": "22:10",
        "filmId": "jugaremos_en_el_bosque",
        "theatre": "8 планет ТЦ Клён",
        "cost": 500,
        "is3d": false,
        "buyLink": null
    },
    {
        "date": "17.09",
        "time": "10:30",
        "filmId": "begi",
        "theatre": "8 планет ТЦ Клён",
        "cost": 300,
        "is3d": false,
        "buyLink": null
    },
    {
        "date": "17.09",
        "time": "10:35",
        "filmId": "vniz",
        "theatre": "8 планет ТЦ Клён",
        "cost": 300,
        "is3d": false,
        "buyLink": null
    },
    {
        "date": "17.09",
        "time": "10:40",
        "filmId": "falcon_express",
        "theatre": "8 планет ТЦ Клён",
        "cost": 300,
        "is3d": false,
        "buyLink": null
    },
    {
        "date": "17.09",
        "time": "12:20",
        "filmId": "kolbasa",
        "theatre": "8 планет ТЦ Клён",
        "cost": 300,
        "is3d": false,
        "buyLink": null
    },
    {
        "date": "17.09",
        "time": "12:30",
        "filmId": "doktor_dinozavrov",
        "theatre": "8 планет ТЦ Клён",
        "cost": 300,
        "is3d": false,
        "buyLink": null
    },
    {
        "date": "17.09",
        "time": "12:35",
        "filmId": "65961",
        "theatre": "8 планет ТЦ Клён",
        "cost": 100,
        "is3d": false,
        "buyLink": null
    },
    {
        "date": "17.09",
        "time": "13:40",
        "filmId": "the_toxic_avenger",
        "theatre": "8 планет ТЦ Клён",
        "cost": 300,
        "is3d": false,
        "buyLink": null
    },
    {
        "date": "17.09",
        "time": "14:25",
        "filmId": "begi",
        "theatre": "8 планет ТЦ Клён",
        "cost": 400,
        "is3d": false,
        "buyLink": null
    },
    {
        "date": "17.09",
        "time": "14:30",
        "filmId": "dracula_a_love_tale",
        "theatre": "8 планет ТЦ Клён",
        "cost": 400,
        "is3d": false,
        "buyLink": null
    },
    {
        "date": "17.09",
        "time": "15:50",
        "filmId": "vniz",
        "theatre": "8 планет ТЦ Клён",
        "cost": 400,
        "is3d": false,
        "buyLink": null
    },
    {
        "date": "17.09",
        "time": "16:20",
        "filmId": "semejnyj_prizrak",
        "theatre": "8 планет ТЦ Клён",
        "cost": 400,
        "is3d": false,
        "buyLink": null
    },
    {
        "date": "17.09",
        "time": "16:50",
        "filmId": "dracula_a_love_tale",
        "theatre": "8 планет ТЦ Клён",
        "cost": 1000,
        "is3d": false,
        "buyLink": null
    },
    {
        "date": "17.09",
        "time": "17:05",
        "filmId": "falcon_express",
        "theatre": "8 планет ТЦ Клён",
        "cost": 400,
        "is3d": false,
        "buyLink": null
    },
    {
        "date": "17.09",
        "time": "17:50",
        "filmId": "doktor_dinozavrov",
        "theatre": "8 планет ТЦ Клён",
        "cost": 450,
        "is3d": false,
        "buyLink": null
    },
    {
        "date": "17.09",
        "time": "18:20",
        "filmId": "begi",
        "theatre": "8 планет ТЦ Клён",
        "cost": 450,
        "is3d": false,
        "buyLink": null
    },
    {
        "date": "17.09",
        "time": "19:00",
        "filmId": "dracula_a_love_tale",
        "theatre": "8 планет ТЦ Клён",
        "cost": 450,
        "is3d": false,
        "buyLink": null
    },
    {
        "date": "17.09",
        "time": "19:30",
        "filmId": "begi",
        "theatre": "8 планет ТЦ Клён",
        "cost": 1000,
        "is3d": false,
        "buyLink": null
    },
    {
        "date": "17.09",
        "time": "19:55",
        "filmId": "8ban_deguchi",
        "theatre": "8 планет ТЦ Клён",
        "cost": 450,
        "is3d": false,
        "buyLink": null
    },
    {
        "date": "17.09",
        "time": "20:15",
        "filmId": "somnium",
        "theatre": "8 планет ТЦ Клён",
        "cost": 450,
        "is3d": false,
        "buyLink": null
    },
    {
        "date": "17.09",
        "time": "21:25",
        "filmId": "nan_jing_zhao_xiang_guan",
        "theatre": "8 планет ТЦ Клён",
        "cost": 1000,
        "is3d": false,
        "buyLink": null
    },
    {
        "date": "17.09",
        "time": "21:35",
        "filmId": "dracula_a_love_tale",
        "theatre": "8 планет ТЦ Клён",
        "cost": 450,
        "is3d": false,
        "buyLink": null
    },
    {
        "date": "17.09",
        "time": "22:00",
        "filmId": "vniz",
        "theatre": "8 планет ТЦ Клён",
        "cost": 450,
        "is3d": false,
        "buyLink": null
    },
    {
        "date": "17.09",
        "time": "22:10",
        "filmId": "jugaremos_en_el_bosque",
        "theatre": "8 планет ТЦ Клён",
        "cost": 450,
        "is3d": false,
        "buyLink": null
    },
    {
        "date": "18.09",
        "time": "10:30",
        "filmId": "begi",
        "theatre": "8 планет ТЦ Клён",
        "cost": 300,
        "is3d": false,
        "buyLink": null
    },
    {
        "date": "18.09",
        "time": "10:35",
        "filmId": "vniz",
        "theatre": "8 планет ТЦ Клён",
        "cost": 300,
        "is3d": false,
        "buyLink": null
    },
    {
        "date": "18.09",
        "time": "10:40",
        "filmId": "falcon_express",
        "theatre": "8 планет ТЦ Клён",
        "cost": 300,
        "is3d": false,
        "buyLink": null
    },
    {
        "date": "18.09",
        "time": "12:20",
        "filmId": "kolbasa",
        "theatre": "8 планет ТЦ Клён",
        "cost": 300,
        "is3d": false,
        "buyLink": null
    },
    {
        "date": "18.09",
        "time": "12:30",
        "filmId": "doktor_dinozavrov",
        "theatre": "8 планет ТЦ Клён",
        "cost": 300,
        "is3d": false,
        "buyLink": null
    },
    {
        "date": "18.09",
        "time": "12:35",
        "filmId": "65961",
        "theatre": "8 планет ТЦ Клён",
        "cost": 100,
        "is3d": false,
        "buyLink": null
    },
    {
        "date": "18.09",
        "time": "13:40",
        "filmId": "the_toxic_avenger",
        "theatre": "8 планет ТЦ Клён",
        "cost": 300,
        "is3d": false,
        "buyLink": null
    },
    {
        "date": "18.09",
        "time": "14:25",
        "filmId": "begi",
        "theatre": "8 планет ТЦ Клён",
        "cost": 400,
        "is3d": false,
        "buyLink": null
    },
    {
        "date": "18.09",
        "time": "14:30",
        "filmId": "dracula_a_love_tale",
        "theatre": "8 планет ТЦ Клён",
        "cost": 400,
        "is3d": false,
        "buyLink": null
    },
    {
        "date": "18.09",
        "time": "15:50",
        "filmId": "vniz",
        "theatre": "8 планет ТЦ Клён",
        "cost": 400,
        "is3d": false,
        "buyLink": null
    },
    {
        "date": "18.09",
        "time": "16:20",
        "filmId": "semejnyj_prizrak",
        "theatre": "8 планет ТЦ Клён",
        "cost": 400,
        "is3d": false,
        "buyLink": null
    },
    {
        "date": "18.09",
        "time": "16:50",
        "filmId": "dracula_a_love_tale",
        "theatre": "8 планет ТЦ Клён",
        "cost": 1000,
        "is3d": false,
        "buyLink": null
    },
    {
        "date": "18.09",
        "time": "17:05",
        "filmId": "falcon_express",
        "theatre": "8 планет ТЦ Клён",
        "cost": 400,
        "is3d": false,
        "buyLink": null
    },
    {
        "date": "18.09",
        "time": "17:50",
        "filmId": "doktor_dinozavrov",
        "theatre": "8 планет ТЦ Клён",
        "cost": 450,
        "is3d": false,
        "buyLink": null
    },
    {
        "date": "18.09",
        "time": "18:20",
        "filmId": "begi",
        "theatre": "8 планет ТЦ Клён",
        "cost": 450,
        "is3d": false,
        "buyLink": null
    },
    {
        "date": "18.09",
        "time": "19:00",
        "filmId": "dracula_a_love_tale",
        "theatre": "8 планет ТЦ Клён",
        "cost": 450,
        "is3d": false,
        "buyLink": null
    },
    {
        "date": "18.09",
        "time": "19:30",
        "filmId": "begi",
        "theatre": "8 планет ТЦ Клён",
        "cost": 1000,
        "is3d": false,
        "buyLink": null
    },
    {
        "date": "18.09",
        "time": "19:55",
        "filmId": "8ban_deguchi",
        "theatre": "8 планет ТЦ Клён",
        "cost": 450,
        "is3d": false,
        "buyLink": null
    },
    {
        "date": "18.09",
        "time": "20:15",
        "filmId": "somnium",
        "theatre": "8 планет ТЦ Клён",
        "cost": 450,
        "is3d": false,
        "buyLink": null
    },
    {
        "date": "18.09",
        "time": "21:25",
        "filmId": "nan_jing_zhao_xiang_guan",
        "theatre": "8 планет ТЦ Клён",
        "cost": 1000,
        "is3d": false,
        "buyLink": null
    },
    {
        "date": "18.09",
        "time": "21:35",
        "filmId": "dracula_a_love_tale",
        "theatre": "8 планет ТЦ Клён",
        "cost": 450,
        "is3d": false,
        "buyLink": null
    },
    {
        "date": "18.09",
        "time": "22:00",
        "filmId": "vniz",
        "theatre": "8 планет ТЦ Клён",
        "cost": 450,
        "is3d": false,
        "buyLink": null
    },
    {
        "date": "18.09",
        "time": "22:10",
        "filmId": "jugaremos_en_el_bosque",
        "theatre": "8 планет ТЦ Клён",
        "cost": 450,
        "is3d": false,
        "buyLink": null
    },
    {
        "date": "19.09",
        "time": "10:30",
        "filmId": "begi",
        "theatre": "8 планет ТЦ Клён",
        "cost": 300,
        "is3d": false,
        "buyLink": null
    },
    {
        "date": "19.09",
        "time": "10:35",
        "filmId": "vniz",
        "theatre": "8 планет ТЦ Клён",
        "cost": 300,
        "is3d": false,
        "buyLink": null
    },
    {
        "date": "19.09",
        "time": "10:40",
        "filmId": "falcon_express",
        "theatre": "8 планет ТЦ Клён",
        "cost": 300,
        "is3d": false,
        "buyLink": null
    },
    {
        "date": "19.09",
        "time": "12:20",
        "filmId": "kolbasa",
        "theatre": "8 планет ТЦ Клён",
        "cost": 300,
        "is3d": false,
        "buyLink": null
    },
    {
        "date": "19.09",
        "time": "12:30",
        "filmId": "doktor_dinozavrov",
        "theatre": "8 планет ТЦ Клён",
        "cost": 300,
        "is3d": false,
        "buyLink": null
    },
    {
        "date": "19.09",
        "time": "12:35",
        "filmId": "65961",
        "theatre": "8 планет ТЦ Клён",
        "cost": 100,
        "is3d": false,
        "buyLink": null
    },
    {
        "date": "19.09",
        "time": "13:40",
        "filmId": "the_toxic_avenger",
        "theatre": "8 планет ТЦ Клён",
        "cost": 300,
        "is3d": false,
        "buyLink": null
    },
    {
        "date": "19.09",
        "time": "14:25",
        "filmId": "begi",
        "theatre": "8 планет ТЦ Клён",
        "cost": 400,
        "is3d": false,
        "buyLink": null
    },
    {
        "date": "19.09",
        "time": "14:30",
        "filmId": "dracula_a_love_tale",
        "theatre": "8 планет ТЦ Клён",
        "cost": 400,
        "is3d": false,
        "buyLink": null
    },
    {
        "date": "19.09",
        "time": "15:50",
        "filmId": "vniz",
        "theatre": "8 планет ТЦ Клён",
        "cost": 400,
        "is3d": false,
        "buyLink": null
    },
    {
        "date": "19.09",
        "time": "16:20",
        "filmId": "semejnyj_prizrak",
        "theatre": "8 планет ТЦ Клён",
        "cost": 400,
        "is3d": false,
        "buyLink": null
    },
    {
        "date": "19.09",
        "time": "16:50",
        "filmId": "dracula_a_love_tale",
        "theatre": "8 планет ТЦ Клён",
        "cost": 1000,
        "is3d": false,
        "buyLink": null
    },
    {
        "date": "19.09",
        "time": "17:05",
        "filmId": "falcon_express",
        "theatre": "8 планет ТЦ Клён",
        "cost": 400,
        "is3d": false,
        "buyLink": null
    },
    {
        "date": "19.09",
        "time": "17:50",
        "filmId": "doktor_dinozavrov",
        "theatre": "8 планет ТЦ Клён",
        "cost": 450,
        "is3d": false,
        "buyLink": null
    },
    {
        "date": "19.09",
        "time": "18:20",
        "filmId": "begi",
        "theatre": "8 планет ТЦ Клён",
        "cost": 450,
        "is3d": false,
        "buyLink": null
    },
    {
        "date": "19.09",
        "time": "19:00",
        "filmId": "dracula_a_love_tale",
        "theatre": "8 планет ТЦ Клён",
        "cost": 450,
        "is3d": false,
        "buyLink": null
    },
    {
        "date": "19.09",
        "time": "19:30",
        "filmId": "begi",
        "theatre": "8 планет ТЦ Клён",
        "cost": 1000,
        "is3d": false,
        "buyLink": null
    },
    {
        "date": "19.09",
        "time": "19:55",
        "filmId": "8ban_deguchi",
        "theatre": "8 планет ТЦ Клён",
        "cost": 450,
        "is3d": false,
        "buyLink": null
    },
    {
        "date": "19.09",
        "time": "20:15",
        "filmId": "somnium",
        "theatre": "8 планет ТЦ Клён",
        "cost": 450,
        "is3d": false,
        "buyLink": null
    },
    {
        "date": "19.09",
        "time": "21:25",
        "filmId": "nan_jing_zhao_xiang_guan",
        "theatre": "8 планет ТЦ Клён",
        "cost": 1000,
        "is3d": false,
        "buyLink": null
    },
    {
        "date": "19.09",
        "time": "21:35",
        "filmId": "dracula_a_love_tale",
        "theatre": "8 планет ТЦ Клён",
        "cost": 450,
        "is3d": false,
        "buyLink": null
    },
    {
        "date": "19.09",
        "time": "22:00",
        "filmId": "vniz",
        "theatre": "8 планет ТЦ Клён",
        "cost": 450,
        "is3d": false,
        "buyLink": null
    },
    {
        "date": "19.09",
        "time": "22:10",
        "filmId": "jugaremos_en_el_bosque",
        "theatre": "8 планет ТЦ Клён",
        "cost": 450,
        "is3d": false,
        "buyLink": null
    }
]