[
    {
        "date": "10.11",
        "time": "22:00",
        "filmId": "mazhor_v_dubae",
        "theatre": "Аврора",
        "cost": 350,
        "is3d": false,
        "buyLink": null
    },
    {
        "date": "11.11",
        "time": "10:00",
        "filmId": "alisa_v_strane_chudes",
        "theatre": "Аврора",
        "cost": 320,
        "is3d": false,
        "buyLink": null
    },
    {
        "date": "11.11",
        "time": "12:15",
        "filmId": "gorynych",
        "theatre": "Аврора",
        "cost": 350,
        "is3d": false,
        "buyLink": null
    },
    {
        "date": "11.11",
        "time": "14:15",
        "filmId": "papiny_dochki_mama_vernulas",
        "theatre": "Аврора",
        "cost": 320,
        "is3d": false,
        "buyLink": null
    },
    {
        "date": "11.11",
        "time": "16:10",
        "filmId": "hopper_et_le_secret_de_la_marm",
        "theatre": "Аврора",
        "cost": 350,
        "is3d": false,
        "buyLink": null
    },
    {
        "date": "11.11",
        "time": "18:00",
        "filmId": "mazhor_v_dubae",
        "theatre": "Аврора",
        "cost": 350,
        "is3d": false,
        "buyLink": null
    },
    {
        "date": "11.11",
        "time": "20:25",
        "filmId": "golosovoj_pomoshnik",
        "theatre": "Аврора",
        "cost": 370,
        "is3d": false,
        "buyLink": null
    },
    {
        "date": "11.11",
        "time": "22:30",
        "filmId": "finnik_2",
        "theatre": "Аврора",
        "cost": 300,
        "is3d": false,
        "buyLink": null
    },
    {
        "date": "12.11",
        "time": "10:00",
        "filmId": "alisa_v_strane_chudes",
        "theatre": "Аврора",
        "cost": 280,
        "is3d": false,
        "buyLink": null
    },
    {
        "date": "12.11",
        "time": "12:15",
        "filmId": "hopper_et_le_secret_de_la_marm",
        "theatre": "Аврора",
        "cost": 350,
        "is3d": false,
        "buyLink": null
    },
    {
        "date": "12.11",
        "time": "14:05",
        "filmId": "papiny_dochki_mama_vernulas",
        "theatre": "Аврора",
        "cost": 280,
        "is3d": false,
        "buyLink": null
    },
    {
        "date": "12.11",
        "time": "16:00",
        "filmId": "gorynych",
        "theatre": "Аврора",
        "cost": 280,
        "is3d": false,
        "buyLink": null
    },
    {
        "date": "12.11",
        "time": "18:00",
        "filmId": "finnik_2",
        "theatre": "Аврора",
        "cost": 280,
        "is3d": false,
        "buyLink": null
    },
    {
        "date": "12.11",
        "time": "19:50",
        "filmId": "golosovoj_pomoshnik",
        "theatre": "Аврора",
        "cost": 370,
        "is3d": false,
        "buyLink": null
    },
    {
        "date": "12.11",
        "time": "21:55",
        "filmId": "mazhor_v_dubae",
        "theatre": "Аврора",
        "cost": 320,
        "is3d": false,
        "buyLink": null
    }
]