[
    {
        "date": "10.08",
        "time": "09:55",
        "filmId": "53813",
        "theatre": "Аврора",
        "cost": 260,
        "is3d": false,
        "seanceId": 0
    },
    {
        "date": "10.08",
        "time": "10:00",
        "filmId": "53670",
        "theatre": "Аврора",
        "cost": 260,
        "is3d": false,
        "seanceId": 1
    },
    {
        "date": "10.08",
        "time": "11:40",
        "filmId": "53677",
        "theatre": "Аврора",
        "cost": 260,
        "is3d": false,
        "seanceId": 2
    },
    {
        "date": "10.08",
        "time": "11:55",
        "filmId": "53572",
        "theatre": "Аврора",
        "cost": 280,
        "is3d": false,
        "seanceId": 3
    },
    {
        "date": "10.08",
        "time": "13:25",
        "filmId": "52334",
        "theatre": "Аврора",
        "cost": 280,
        "is3d": false,
        "seanceId": 4
    },
    {
        "date": "10.08",
        "time": "13:55",
        "filmId": "53813",
        "theatre": "Аврора",
        "cost": 260,
        "is3d": false,
        "seanceId": 5
    },
    {
        "date": "10.08",
        "time": "15:20",
        "filmId": "52335",
        "theatre": "Аврора",
        "cost": 300,
        "is3d": true,
        "seanceId": 6
    },
    {
        "date": "10.08",
        "time": "15:55",
        "filmId": "53572",
        "theatre": "Аврора",
        "cost": 280,
        "is3d": false,
        "seanceId": 7
    },
    {
        "date": "10.08",
        "time": "17:40",
        "filmId": "52334",
        "theatre": "Аврора",
        "cost": 280,
        "is3d": false,
        "seanceId": 8
    },
    {
        "date": "10.08",
        "time": "17:55",
        "filmId": "31764",
        "theatre": "Аврора",
        "cost": 240,
        "is3d": false,
        "seanceId": 9
    },
    {
        "date": "10.08",
        "time": "19:35",
        "filmId": "52335",
        "theatre": "Аврора",
        "cost": 300,
        "is3d": true,
        "seanceId": 10
    },
    {
        "date": "10.08",
        "time": "20:15",
        "filmId": "53668",
        "theatre": "Аврора",
        "cost": 280,
        "is3d": false,
        "seanceId": 11
    },
    {
        "date": "10.08",
        "time": "21:55",
        "filmId": "53572",
        "theatre": "Аврора",
        "cost": 280,
        "is3d": false,
        "seanceId": 12
    },
    {
        "date": "10.08",
        "time": "22:05",
        "filmId": "53676",
        "theatre": "Аврора",
        "cost": 260,
        "is3d": false,
        "seanceId": 13
    },
    {
        "date": "10.08",
        "time": "23:45",
        "filmId": "53675",
        "theatre": "Аврора",
        "cost": 260,
        "is3d": false,
        "seanceId": 14
    },
    {
        "date": "10.08",
        "time": "23:55",
        "filmId": "53676",
        "theatre": "Аврора",
        "cost": 260,
        "is3d": false,
        "seanceId": 15
    },
    {
        "date": "11.08",
        "time": "09:55",
        "filmId": "53813",
        "theatre": "Аврора",
        "cost": 260,
        "is3d": false,
        "seanceId": 16
    },
    {
        "date": "11.08",
        "time": "10:00",
        "filmId": "53670",
        "theatre": "Аврора",
        "cost": 260,
        "is3d": false,
        "seanceId": 17
    },
    {
        "date": "11.08",
        "time": "11:40",
        "filmId": "53677",
        "theatre": "Аврора",
        "cost": 260,
        "is3d": false,
        "seanceId": 18
    },
    {
        "date": "11.08",
        "time": "11:55",
        "filmId": "53572",
        "theatre": "Аврора",
        "cost": 280,
        "is3d": false,
        "seanceId": 19
    },
    {
        "date": "11.08",
        "time": "13:25",
        "filmId": "52334",
        "theatre": "Аврора",
        "cost": 280,
        "is3d": false,
        "seanceId": 20
    },
    {
        "date": "11.08",
        "time": "13:55",
        "filmId": "53813",
        "theatre": "Аврора",
        "cost": 260,
        "is3d": false,
        "seanceId": 21
    },
    {
        "date": "11.08",
        "time": "15:20",
        "filmId": "52335",
        "theatre": "Аврора",
        "cost": 300,
        "is3d": true,
        "seanceId": 22
    },
    {
        "date": "11.08",
        "time": "15:55",
        "filmId": "53572",
        "theatre": "Аврора",
        "cost": 280,
        "is3d": false,
        "seanceId": 23
    },
    {
        "date": "11.08",
        "time": "17:40",
        "filmId": "52334",
        "theatre": "Аврора",
        "cost": 280,
        "is3d": false,
        "seanceId": 24
    },
    {
        "date": "11.08",
        "time": "17:55",
        "filmId": "31764",
        "theatre": "Аврора",
        "cost": 240,
        "is3d": false,
        "seanceId": 25
    },
    {
        "date": "11.08",
        "time": "19:35",
        "filmId": "52335",
        "theatre": "Аврора",
        "cost": 300,
        "is3d": true,
        "seanceId": 26
    },
    {
        "date": "11.08",
        "time": "20:15",
        "filmId": "53668",
        "theatre": "Аврора",
        "cost": 280,
        "is3d": false,
        "seanceId": 27
    },
    {
        "date": "11.08",
        "time": "21:55",
        "filmId": "53572",
        "theatre": "Аврора",
        "cost": 280,
        "is3d": false,
        "seanceId": 28
    },
    {
        "date": "11.08",
        "time": "22:05",
        "filmId": "53676",
        "theatre": "Аврора",
        "cost": 260,
        "is3d": false,
        "seanceId": 29
    },
    {
        "date": "11.08",
        "time": "23:45",
        "filmId": "53675",
        "theatre": "Аврора",
        "cost": 260,
        "is3d": false,
        "seanceId": 30
    },
    {
        "date": "11.08",
        "time": "23:55",
        "filmId": "53676",
        "theatre": "Аврора",
        "cost": 260,
        "is3d": false,
        "seanceId": 31
    },
    {
        "date": "12.08",
        "time": "10:00",
        "filmId": "53813",
        "theatre": "Аврора",
        "cost": 260,
        "is3d": false,
        "seanceId": 32
    },
    {
        "date": "12.08",
        "time": "10:00",
        "filmId": "53670",
        "theatre": "Аврора",
        "cost": 260,
        "is3d": false,
        "seanceId": 33
    },
    {
        "date": "12.08",
        "time": "11:40",
        "filmId": "52335",
        "theatre": "Аврора",
        "cost": 300,
        "is3d": true,
        "seanceId": 34
    },
    {
        "date": "12.08",
        "time": "12:00",
        "filmId": "53677",
        "theatre": "Аврора",
        "cost": 260,
        "is3d": false,
        "seanceId": 35
    },
    {
        "date": "12.08",
        "time": "13:50",
        "filmId": "53572",
        "theatre": "Аврора",
        "cost": 280,
        "is3d": false,
        "seanceId": 36
    },
    {
        "date": "12.08",
        "time": "14:00",
        "filmId": "52334",
        "theatre": "Аврора",
        "cost": 280,
        "is3d": false,
        "seanceId": 37
    },
    {
        "date": "12.08",
        "time": "15:50",
        "filmId": "31764",
        "theatre": "Аврора",
        "cost": 240,
        "is3d": false,
        "seanceId": 38
    },
    {
        "date": "12.08",
        "time": "16:00",
        "filmId": "52334",
        "theatre": "Аврора",
        "cost": 280,
        "is3d": false,
        "seanceId": 39
    },
    {
        "date": "12.08",
        "time": "18:00",
        "filmId": "52335",
        "theatre": "Аврора",
        "cost": 300,
        "is3d": true,
        "seanceId": 40
    },
    {
        "date": "12.08",
        "time": "18:10",
        "filmId": "53668",
        "theatre": "Аврора",
        "cost": 280,
        "is3d": false,
        "seanceId": 41
    },
    {
        "date": "12.08",
        "time": "20:00",
        "filmId": "53813",
        "theatre": "Аврора",
        "cost": 260,
        "is3d": false,
        "seanceId": 42
    },
    {
        "date": "12.08",
        "time": "20:20",
        "filmId": "53572",
        "theatre": "Аврора",
        "cost": 280,
        "is3d": false,
        "seanceId": 43
    },
    {
        "date": "12.08",
        "time": "22:00",
        "filmId": "53676",
        "theatre": "Аврора",
        "cost": 260,
        "is3d": false,
        "seanceId": 44
    },
    {
        "date": "12.08",
        "time": "22:20",
        "filmId": "53675",
        "theatre": "Аврора",
        "cost": 260,
        "is3d": false,
        "seanceId": 45
    },
    {
        "date": "12.08",
        "time": "23:40",
        "filmId": "53572",
        "theatre": "Аврора",
        "cost": 280,
        "is3d": false,
        "seanceId": 46
    },
    {
        "date": "12.08",
        "time": "23:55",
        "filmId": "53676",
        "theatre": "Аврора",
        "cost": 260,
        "is3d": false,
        "seanceId": 47
    },
    {
        "date": "13.08",
        "time": "10:00",
        "filmId": "53813",
        "theatre": "Аврора",
        "cost": 260,
        "is3d": false,
        "seanceId": 48
    },
    {
        "date": "13.08",
        "time": "10:00",
        "filmId": "53670",
        "theatre": "Аврора",
        "cost": 260,
        "is3d": false,
        "seanceId": 49
    },
    {
        "date": "13.08",
        "time": "11:40",
        "filmId": "52335",
        "theatre": "Аврора",
        "cost": 300,
        "is3d": true,
        "seanceId": 50
    },
    {
        "date": "13.08",
        "time": "12:00",
        "filmId": "53677",
        "theatre": "Аврора",
        "cost": 260,
        "is3d": false,
        "seanceId": 51
    },
    {
        "date": "13.08",
        "time": "13:50",
        "filmId": "53572",
        "theatre": "Аврора",
        "cost": 280,
        "is3d": false,
        "seanceId": 52
    },
    {
        "date": "13.08",
        "time": "14:00",
        "filmId": "52334",
        "theatre": "Аврора",
        "cost": 280,
        "is3d": false,
        "seanceId": 53
    },
    {
        "date": "13.08",
        "time": "15:50",
        "filmId": "31764",
        "theatre": "Аврора",
        "cost": 240,
        "is3d": false,
        "seanceId": 54
    },
    {
        "date": "13.08",
        "time": "16:00",
        "filmId": "52334",
        "theatre": "Аврора",
        "cost": 280,
        "is3d": false,
        "seanceId": 55
    },
    {
        "date": "13.08",
        "time": "18:00",
        "filmId": "52335",
        "theatre": "Аврора",
        "cost": 300,
        "is3d": true,
        "seanceId": 56
    },
    {
        "date": "13.08",
        "time": "18:10",
        "filmId": "53668",
        "theatre": "Аврора",
        "cost": 280,
        "is3d": false,
        "seanceId": 57
    },
    {
        "date": "13.08",
        "time": "20:00",
        "filmId": "53813",
        "theatre": "Аврора",
        "cost": 260,
        "is3d": false,
        "seanceId": 58
    },
    {
        "date": "13.08",
        "time": "20:20",
        "filmId": "53572",
        "theatre": "Аврора",
        "cost": 280,
        "is3d": false,
        "seanceId": 59
    },
    {
        "date": "13.08",
        "time": "22:00",
        "filmId": "53676",
        "theatre": "Аврора",
        "cost": 260,
        "is3d": false,
        "seanceId": 60
    },
    {
        "date": "13.08",
        "time": "22:20",
        "filmId": "53675",
        "theatre": "Аврора",
        "cost": 260,
        "is3d": false,
        "seanceId": 61
    },
    {
        "date": "13.08",
        "time": "23:40",
        "filmId": "53572",
        "theatre": "Аврора",
        "cost": 280,
        "is3d": false,
        "seanceId": 62
    },
    {
        "date": "13.08",
        "time": "23:55",
        "filmId": "53676",
        "theatre": "Аврора",
        "cost": 260,
        "is3d": false,
        "seanceId": 63
    },
    {
        "date": "14.08",
        "time": "10:00",
        "filmId": "53670",
        "theatre": "Аврора",
        "cost": 240,
        "is3d": false,
        "seanceId": 64
    },
    {
        "date": "14.08",
        "time": "10:00",
        "filmId": "53677",
        "theatre": "Аврора",
        "cost": 240,
        "is3d": false,
        "seanceId": 65
    },
    {
        "date": "14.08",
        "time": "11:40",
        "filmId": "53572",
        "theatre": "Аврора",
        "cost": 280,
        "is3d": false,
        "seanceId": 66
    },
    {
        "date": "14.08",
        "time": "11:50",
        "filmId": "53813",
        "theatre": "Аврора",
        "cost": 260,
        "is3d": false,
        "seanceId": 67
    },
    {
        "date": "14.08",
        "time": "13:40",
        "filmId": "31764",
        "theatre": "Аврора",
        "cost": 240,
        "is3d": false,
        "seanceId": 68
    },
    {
        "date": "14.08",
        "time": "13:50",
        "filmId": "52334",
        "theatre": "Аврора",
        "cost": 260,
        "is3d": false,
        "seanceId": 69
    },
    {
        "date": "14.08",
        "time": "15:45",
        "filmId": "52334",
        "theatre": "Аврора",
        "cost": 260,
        "is3d": false,
        "seanceId": 70
    },
    {
        "date": "14.08",
        "time": "15:55",
        "filmId": "53813",
        "theatre": "Аврора",
        "cost": 260,
        "is3d": false,
        "seanceId": 71
    },
    {
        "date": "14.08",
        "time": "17:40",
        "filmId": "52335",
        "theatre": "Аврора",
        "cost": 280,
        "is3d": true,
        "seanceId": 72
    },
    {
        "date": "14.08",
        "time": "17:55",
        "filmId": "53668",
        "theatre": "Аврора",
        "cost": 280,
        "is3d": false,
        "seanceId": 73
    },
    {
        "date": "14.08",
        "time": "19:45",
        "filmId": "53572",
        "theatre": "Аврора",
        "cost": 280,
        "is3d": false,
        "seanceId": 74
    },
    {
        "date": "14.08",
        "time": "20:00",
        "filmId": "52335",
        "theatre": "Аврора",
        "cost": 280,
        "is3d": true,
        "seanceId": 75
    },
    {
        "date": "14.08",
        "time": "21:45",
        "filmId": "53813",
        "theatre": "Аврора",
        "cost": 260,
        "is3d": false,
        "seanceId": 76
    },
    {
        "date": "14.08",
        "time": "22:20",
        "filmId": "53675",
        "theatre": "Аврора",
        "cost": 260,
        "is3d": false,
        "seanceId": 77
    },
    {
        "date": "14.08",
        "time": "23:45",
        "filmId": "53572",
        "theatre": "Аврора",
        "cost": 260,
        "is3d": false,
        "seanceId": 78
    },
    {
        "date": "14.08",
        "time": "23:55",
        "filmId": "53676",
        "theatre": "Аврора",
        "cost": 240,
        "is3d": false,
        "seanceId": 79
    }
]