[
    {
        "date": "05.02",
        "time": "16:30",
        "filmId": "57886",
        "theatre": "Россия",
        "cost": 400,
        "is3d": false,
        "buyLink": null
    },
    {
        "date": "05.02",
        "time": "18:15",
        "filmId": "57613",
        "theatre": "Россия",
        "cost": 450,
        "is3d": false,
        "buyLink": null
    },
    {
        "date": "05.02",
        "time": "18:25",
        "filmId": "57858",
        "theatre": "Россия",
        "cost": 450,
        "is3d": false,
        "buyLink": null
    },
    {
        "date": "05.02",
        "time": "20:25",
        "filmId": "58172",
        "theatre": "Россия",
        "cost": 450,
        "is3d": false,
        "buyLink": null
    },
    {
        "date": "05.02",
        "time": "20:35",
        "filmId": "57639",
        "theatre": "Россия",
        "cost": 450,
        "is3d": false,
        "buyLink": null
    },
    {
        "date": "05.02",
        "time": "22:40",
        "filmId": "57612",
        "theatre": "Россия",
        "cost": 400,
        "is3d": false,
        "buyLink": null
    },
    {
        "date": "05.02",
        "time": "23:00",
        "filmId": "57613",
        "theatre": "Россия",
        "cost": 400,
        "is3d": false,
        "buyLink": null
    }
]