[
    {
        "filmId": "angely_ladogi",
        "name": "Ангелы Ладоги",
        "rating": 12,
        "genres": [
            "драма",
            "история"
        ],
        "length": 110
    },
    {
        "filmId": "the_mummy_2026",
        "name": "Мумия",
        "rating": 18,
        "genres": [
            "ужасы"
        ],
        "length": 135
    },
    {
        "filmId": "kommersant",
        "name": "Коммерсант",
        "rating": 18,
        "genres": [
            "драма"
        ],
        "length": 95
    },
    {
        "filmId": "zolushka_tajna_treh_zhelanij",
        "name": "Золушка. Тайна трёх желаний",
        "rating": 6,
        "genres": [
            "мультфильм",
            "фэнтези"
        ],
        "length": 85
    },
    {
        "filmId": "moja_sobaka_kosmonavt",
        "name": "Моя собака – космонавт",
        "rating": 6,
        "genres": [
            "семейный",
            "приключения",
            "комедия"
        ],
        "length": 105
    },
    {
        "filmId": "the_super_mario_galaxy_movie",
        "name": "Супер Марио: Галактическое кино",
        "rating": 6,
        "genres": [
            "мультфильм",
            "фэнтези",
            "комедия",
            "приключения",
            "семейный"
        ],
        "length": 100
    },
    {
        "filmId": "petrushka",
        "name": "Петрушка",
        "rating": 6,
        "genres": [
            "комедия"
        ],
        "length": 90
    },
    {
        "filmId": "prikljuchenija_zheltogo_chemodanchik",
        "name": "Приключения жёлтого чемоданчика",
        "rating": 6,
        "genres": [
            "приключения",
            "фэнтези",
            "комедия",
            "семейный"
        ],
        "length": 90
    }
]