[
    {
        "filmId": "61414",
        "name": "Бес попутал",
        "rating": 18,
        "genres": [
            "комедия",
            "фэнтези"
        ],
        "length": 80
    },
    {
        "filmId": "60365",
        "name": "Кракен",
        "rating": 12,
        "genres": [
            "фантастика",
            "приключения",
            "боевик"
        ],
        "length": 135
    },
    {
        "filmId": "61439",
        "name": "Кукла. Реинкарнация",
        "rating": 18,
        "genres": [
            "ужасы",
            "фантастика",
            "триллер"
        ],
        "length": 90
    }
]