[
    {
        "filmId": "59352",
        "name": "Киллер в отставке",
        "rating": 16,
        "genres": [
            "боевик",
            "комедия"
        ],
        "length": 95
    },
    {
        "filmId": "58982",
        "name": "Ужасающие",
        "rating": 18,
        "genres": [
            "ужасы"
        ],
        "length": 90
    },
    {
        "filmId": "58672",
        "name": "В потерянных землях",
        "rating": 18,
        "genres": [
            "фэнтези",
            "боевик",
            "приключения"
        ],
        "length": 100
    }
]