[
    {
        "date": "20.02",
        "time": "17:00",
        "filmId": "skazka_o_care_saltane",
        "theatre": "Шахтёр",
        "cost": 420,
        "is3d": false,
        "buyLink": null
    },
    {
        "date": "20.02",
        "time": "18:10",
        "filmId": "uvolit_zhoru",
        "theatre": "Шахтёр",
        "cost": 470,
        "is3d": false,
        "buyLink": null
    },
    {
        "date": "20.02",
        "time": "18:45",
        "filmId": "skazka_o_care_saltane",
        "theatre": "Шахтёр",
        "cost": 470,
        "is3d": false,
        "buyLink": null
    },
    {
        "date": "20.02",
        "time": "19:10",
        "filmId": "korol_i_shut_navsegda",
        "theatre": "Шахтёр",
        "cost": 470,
        "is3d": false,
        "buyLink": null
    },
    {
        "date": "20.02",
        "time": "20:00",
        "filmId": "wuthering_heights",
        "theatre": "Шахтёр",
        "cost": 470,
        "is3d": false,
        "buyLink": null
    },
    {
        "date": "20.02",
        "time": "20:50",
        "filmId": "the_grieving",
        "theatre": "Шахтёр",
        "cost": 470,
        "is3d": false,
        "buyLink": null
    },
    {
        "date": "20.02",
        "time": "21:30",
        "filmId": "the_housemaid",
        "theatre": "Шахтёр",
        "cost": 470,
        "is3d": false,
        "buyLink": null
    },
    {
        "date": "20.02",
        "time": "22:25",
        "filmId": "wuthering_heights",
        "theatre": "Шахтёр",
        "cost": 470,
        "is3d": false,
        "buyLink": null
    },
    {
        "date": "20.02",
        "time": "22:35",
        "filmId": "guantanamera",
        "theatre": "Шахтёр",
        "cost": 470,
        "is3d": false,
        "buyLink": null
    },
    {
        "date": "21.02",
        "time": "09:50",
        "filmId": "krasavica",
        "theatre": "Шахтёр",
        "cost": 320,
        "is3d": false,
        "buyLink": null
    },
    {
        "date": "21.02",
        "time": "10:00",
        "filmId": "les_legendaires",
        "theatre": "Шахтёр",
        "cost": 320,
        "is3d": false,
        "buyLink": null
    },
    {
        "date": "21.02",
        "time": "10:10",
        "filmId": "skazka_o_care_saltane",
        "theatre": "Шахтёр",
        "cost": 320,
        "is3d": false,
        "buyLink": null
    },
    {
        "date": "21.02",
        "time": "11:45",
        "filmId": "krasavica",
        "theatre": "Шахтёр",
        "cost": 350,
        "is3d": false,
        "buyLink": null
    },
    {
        "date": "21.02",
        "time": "11:55",
        "filmId": "guantanamera",
        "theatre": "Шахтёр",
        "cost": 350,
        "is3d": false,
        "buyLink": null
    },
    {
        "date": "21.02",
        "time": "12:20",
        "filmId": "skazka_o_care_saltane",
        "theatre": "Шахтёр",
        "cost": 460,
        "is3d": false,
        "buyLink": null
    },
    {
        "date": "21.02",
        "time": "13:50",
        "filmId": "krasavica",
        "theatre": "Шахтёр",
        "cost": 460,
        "is3d": false,
        "buyLink": null
    },
    {
        "date": "21.02",
        "time": "14:00",
        "filmId": "korol_i_shut_navsegda",
        "theatre": "Шахтёр",
        "cost": 460,
        "is3d": false,
        "buyLink": null
    },
    {
        "date": "21.02",
        "time": "14:30",
        "filmId": "skazka_o_care_saltane",
        "theatre": "Шахтёр",
        "cost": 460,
        "is3d": false,
        "buyLink": null
    },
    {
        "date": "21.02",
        "time": "15:55",
        "filmId": "krasavica",
        "theatre": "Шахтёр",
        "cost": 500,
        "is3d": false,
        "buyLink": null
    },
    {
        "date": "21.02",
        "time": "16:15",
        "filmId": "avatar_fire_and_ash",
        "theatre": "Шахтёр",
        "cost": 580,
        "is3d": false,
        "buyLink": null
    },
    {
        "date": "21.02",
        "time": "16:40",
        "filmId": "stray_kids_the_dominate",
        "theatre": "Шахтёр",
        "cost": 600,
        "is3d": false,
        "buyLink": null
    },
    {
        "date": "21.02",
        "time": "18:00",
        "filmId": "guantanamera",
        "theatre": "Шахтёр",
        "cost": 500,
        "is3d": false,
        "buyLink": null
    },
    {
        "date": "21.02",
        "time": "19:35",
        "filmId": "skazka_o_care_saltane",
        "theatre": "Шахтёр",
        "cost": 500,
        "is3d": false,
        "buyLink": null
    },
    {
        "date": "21.02",
        "time": "19:45",
        "filmId": "wuthering_heights",
        "theatre": "Шахтёр",
        "cost": 500,
        "is3d": false,
        "buyLink": null
    },
    {
        "date": "21.02",
        "time": "20:05",
        "filmId": "korol_i_shut_navsegda",
        "theatre": "Шахтёр",
        "cost": 500,
        "is3d": false,
        "buyLink": null
    },
    {
        "date": "21.02",
        "time": "21:45",
        "filmId": "the_housemaid",
        "theatre": "Шахтёр",
        "cost": 500,
        "is3d": false,
        "buyLink": null
    },
    {
        "date": "21.02",
        "time": "22:15",
        "filmId": "uvolit_zhoru",
        "theatre": "Шахтёр",
        "cost": 500,
        "is3d": false,
        "buyLink": null
    },
    {
        "date": "21.02",
        "time": "22:20",
        "filmId": "the_grieving",
        "theatre": "Шахтёр",
        "cost": 500,
        "is3d": false,
        "buyLink": null
    },
    {
        "date": "22.02",
        "time": "09:50",
        "filmId": "krasavica",
        "theatre": "Шахтёр",
        "cost": 320,
        "is3d": false,
        "buyLink": null
    },
    {
        "date": "22.02",
        "time": "10:00",
        "filmId": "les_legendaires",
        "theatre": "Шахтёр",
        "cost": 320,
        "is3d": false,
        "buyLink": null
    },
    {
        "date": "22.02",
        "time": "10:10",
        "filmId": "skazka_o_care_saltane",
        "theatre": "Шахтёр",
        "cost": 320,
        "is3d": false,
        "buyLink": null
    },
    {
        "date": "22.02",
        "time": "11:45",
        "filmId": "krasavica",
        "theatre": "Шахтёр",
        "cost": 350,
        "is3d": false,
        "buyLink": null
    },
    {
        "date": "22.02",
        "time": "11:55",
        "filmId": "guantanamera",
        "theatre": "Шахтёр",
        "cost": 350,
        "is3d": false,
        "buyLink": null
    },
    {
        "date": "22.02",
        "time": "12:25",
        "filmId": "skazka_o_care_saltane",
        "theatre": "Шахтёр",
        "cost": 460,
        "is3d": false,
        "buyLink": null
    },
    {
        "date": "22.02",
        "time": "13:50",
        "filmId": "krasavica",
        "theatre": "Шахтёр",
        "cost": 460,
        "is3d": false,
        "buyLink": null
    },
    {
        "date": "22.02",
        "time": "14:00",
        "filmId": "korol_i_shut_navsegda",
        "theatre": "Шахтёр",
        "cost": 460,
        "is3d": false,
        "buyLink": null
    },
    {
        "date": "22.02",
        "time": "14:40",
        "filmId": "skazka_o_care_saltane",
        "theatre": "Шахтёр",
        "cost": 460,
        "is3d": false,
        "buyLink": null
    },
    {
        "date": "22.02",
        "time": "16:00",
        "filmId": "vlastelin_kolec_dve_kreposti",
        "theatre": "Шахтёр",
        "cost": 460,
        "is3d": false,
        "buyLink": null
    },
    {
        "date": "22.02",
        "time": "16:15",
        "filmId": "avatar_fire_and_ash",
        "theatre": "Шахтёр",
        "cost": 580,
        "is3d": false,
        "buyLink": null
    },
    {
        "date": "22.02",
        "time": "16:55",
        "filmId": "uvolit_zhoru",
        "theatre": "Шахтёр",
        "cost": 500,
        "is3d": false,
        "buyLink": null
    },
    {
        "date": "22.02",
        "time": "18:55",
        "filmId": "skazka_o_care_saltane",
        "theatre": "Шахтёр",
        "cost": 500,
        "is3d": false,
        "buyLink": null
    },
    {
        "date": "22.02",
        "time": "19:20",
        "filmId": "korol_i_shut_navsegda",
        "theatre": "Шахтёр",
        "cost": 500,
        "is3d": false,
        "buyLink": null
    },
    {
        "date": "22.02",
        "time": "19:45",
        "filmId": "wuthering_heights",
        "theatre": "Шахтёр",
        "cost": 500,
        "is3d": false,
        "buyLink": null
    },
    {
        "date": "22.02",
        "time": "21:10",
        "filmId": "the_housemaid",
        "theatre": "Шахтёр",
        "cost": 500,
        "is3d": false,
        "buyLink": null
    },
    {
        "date": "22.02",
        "time": "21:35",
        "filmId": "guantanamera",
        "theatre": "Шахтёр",
        "cost": 500,
        "is3d": false,
        "buyLink": null
    },
    {
        "date": "22.02",
        "time": "22:15",
        "filmId": "the_grieving",
        "theatre": "Шахтёр",
        "cost": 500,
        "is3d": false,
        "buyLink": null
    },
    {
        "date": "23.02",
        "time": "10:00",
        "filmId": "les_legendaires",
        "theatre": "Шахтёр",
        "cost": 320,
        "is3d": false,
        "buyLink": null
    },
    {
        "date": "23.02",
        "time": "10:10",
        "filmId": "skazka_o_care_saltane",
        "theatre": "Шахтёр",
        "cost": 320,
        "is3d": false,
        "buyLink": null
    },
    {
        "date": "23.02",
        "time": "10:40",
        "filmId": "guantanamera",
        "theatre": "Шахтёр",
        "cost": 350,
        "is3d": false,
        "buyLink": null
    },
    {
        "date": "23.02",
        "time": "11:50",
        "filmId": "krasavica",
        "theatre": "Шахтёр",
        "cost": 350,
        "is3d": false,
        "buyLink": null
    },
    {
        "date": "23.02",
        "time": "12:25",
        "filmId": "skazka_o_care_saltane",
        "theatre": "Шахтёр",
        "cost": 460,
        "is3d": false,
        "buyLink": null
    },
    {
        "date": "23.02",
        "time": "13:55",
        "filmId": "krasavica",
        "theatre": "Шахтёр",
        "cost": 460,
        "is3d": false,
        "buyLink": null
    },
    {
        "date": "23.02",
        "time": "14:00",
        "filmId": "korol_i_shut_navsegda",
        "theatre": "Шахтёр",
        "cost": 460,
        "is3d": false,
        "buyLink": null
    },
    {
        "date": "23.02",
        "time": "14:40",
        "filmId": "skazka_o_care_saltane",
        "theatre": "Шахтёр",
        "cost": 460,
        "is3d": false,
        "buyLink": null
    },
    {
        "date": "23.02",
        "time": "16:00",
        "filmId": "uvolit_zhoru",
        "theatre": "Шахтёр",
        "cost": 460,
        "is3d": false,
        "buyLink": null
    },
    {
        "date": "23.02",
        "time": "16:15",
        "filmId": "avatar_fire_and_ash",
        "theatre": "Шахтёр",
        "cost": 580,
        "is3d": false,
        "buyLink": null
    },
    {
        "date": "23.02",
        "time": "16:55",
        "filmId": "krasavica",
        "theatre": "Шахтёр",
        "cost": 500,
        "is3d": false,
        "buyLink": null
    },
    {
        "date": "23.02",
        "time": "17:55",
        "filmId": "korol_i_shut_navsegda",
        "theatre": "Шахтёр",
        "cost": 500,
        "is3d": false,
        "buyLink": null
    },
    {
        "date": "23.02",
        "time": "19:10",
        "filmId": "skazka_o_care_saltane",
        "theatre": "Шахтёр",
        "cost": 500,
        "is3d": false,
        "buyLink": null
    },
    {
        "date": "23.02",
        "time": "19:45",
        "filmId": "wuthering_heights",
        "theatre": "Шахтёр",
        "cost": 500,
        "is3d": false,
        "buyLink": null
    },
    {
        "date": "23.02",
        "time": "20:10",
        "filmId": "guantanamera",
        "theatre": "Шахтёр",
        "cost": 500,
        "is3d": false,
        "buyLink": null
    },
    {
        "date": "23.02",
        "time": "21:25",
        "filmId": "the_housemaid",
        "theatre": "Шахтёр",
        "cost": 500,
        "is3d": false,
        "buyLink": null
    },
    {
        "date": "23.02",
        "time": "22:15",
        "filmId": "wuthering_heights",
        "theatre": "Шахтёр",
        "cost": 500,
        "is3d": false,
        "buyLink": null
    },
    {
        "date": "23.02",
        "time": "22:20",
        "filmId": "the_grieving",
        "theatre": "Шахтёр",
        "cost": 500,
        "is3d": false,
        "buyLink": null
    }
]